{
"instructions_readme": "1) Open Chrome, 2) go to chrome://tracing, 3) click Load, 4) navigate to this file.",

"traceEvents":[
{ "pid": 1, "tid": 1, "ph": "M", "name": "thread_name", "args": { "name": "" } },
{ "pid": 1, "tid": 1, "ts": 3.00000002607703, "dur": 120832835.9375, "ph": "X", "name": "il2cpp.exe", "args": { "durationMS": 120832.8359375, "detail": "" } },
{ "pid": 1, "tid": 1, "ts": 415967.803955078, "dur": 23706144.53125, "ph": "X", "name": "ConvertAssemblies", "args": { "durationMS": 23706.14453125, "detail": "" } },
{ "pid": 1, "tid": 1, "ts": 495108.001708984, "dur": 122892.593383789, "ph": "X", "name": "Collect assemblies to convert", "args": { "durationMS": 122.892593383789, "detail": "" } },
{ "pid": 1, "tid": 1, "ts": 618200.1953125, "dur": 85795.9976196289, "ph": "X", "name": "RegisterCorlib", "args": { "durationMS": 85.7959976196289, "detail": "" } },
{ "pid": 1, "tid": 1, "ts": 704341.613769531, "dur": 70137.6037597656, "ph": "X", "name": "PreProcessIL", "args": { "durationMS": 70.1376037597656, "detail": "" } },
{ "pid": 1, "tid": 1, "ts": 704342.102050781, "dur": 18801.2008666992, "ph": "X", "name": "Inject base types and finalizers into COM and Windows Runtime types", "args": { "durationMS": 18.8012008666992, "detail": "" } },
{ "pid": 1, "tid": 1, "ts": 704690.795898438, "dur": 13674.2000579834, "ph": "X", "name": "ModifyCOMAndWindowsRuntimeTypes in assembly", "args": { "durationMS": 13.6742000579834, "detail": "mscorlib" } },
{ "pid": 1, "tid": 1, "ts": 718366.394042969, "dur": 2156.59999847412, "ph": "X", "name": "ModifyCOMAndWindowsRuntimeTypes in assembly", "args": { "durationMS": 2.15659999847412, "detail": "System" } },
{ "pid": 1, "tid": 1, "ts": 720940.612792969, "dur": 1161.00001335144, "ph": "X", "name": "ModifyCOMAndWindowsRuntimeTypes in assembly", "args": { "durationMS": 1.16100001335144, "detail": "UnityEngine.CoreModule" } },
{ "pid": 1, "tid": 1, "ts": 722241.882324219, "dur": 648.299992084503, "ph": "X", "name": "ModifyCOMAndWindowsRuntimeTypes in assembly", "args": { "durationMS": 0.648299992084503, "detail": "UnityEngine.UI" } },
{ "pid": 1, "tid": 1, "ts": 723143.493652344, "dur": 51333.2977294922, "ph": "X", "name": "ApplyDefaultMarshalAsAttribute", "args": { "durationMS": 51.3332977294922, "detail": "" } },
{ "pid": 1, "tid": 1, "ts": 723502.807617188, "dur": 33350.700378418, "ph": "X", "name": "ApplyDefaultMarshalAsAttributeVisitor in assembly", "args": { "durationMS": 33.350700378418, "detail": "mscorlib" } },
{ "pid": 1, "tid": 1, "ts": 756855.102539063, "dur": 4087.90016174316, "ph": "X", "name": "ApplyDefaultMarshalAsAttributeVisitor in assembly", "args": { "durationMS": 4.08790016174316, "detail": "System" } },
{ "pid": 1, "tid": 1, "ts": 761223.205566406, "dur": 1925.40001869202, "ph": "X", "name": "ApplyDefaultMarshalAsAttributeVisitor in assembly", "args": { "durationMS": 1.92540001869202, "detail": "UnityEngine.CoreModule" } },
{ "pid": 1, "tid": 1, "ts": 763152.404785156, "dur": 6975.69990158081, "ph": "X", "name": "ApplyDefaultMarshalAsAttributeVisitor in assembly", "args": { "durationMS": 6.97569990158081, "detail": "UnityEngine.TextRenderingModule" } },
{ "pid": 1, "tid": 1, "ts": 770893.188476563, "dur": 1851.19998455048, "ph": "X", "name": "ApplyDefaultMarshalAsAttributeVisitor in assembly", "args": { "durationMS": 1.85119998455048, "detail": "UnityEngine.UI" } },
{ "pid": 1, "tid": 1, "ts": 772788.696289063, "dur": 662.10001707077, "ph": "X", "name": "ApplyDefaultMarshalAsAttributeVisitor in assembly", "args": { "durationMS": 0.66210001707077, "detail": "LeanTransition" } },
{ "pid": 1, "tid": 1, "ts": 773572.204589844, "dur": 443.399995565414, "ph": "X", "name": "ApplyDefaultMarshalAsAttributeVisitor in assembly", "args": { "durationMS": 0.443399995565414, "detail": "LeanGUI" } },
{ "pid": 1, "tid": 1, "ts": 774065.490722656, "dur": 404.599994421005, "ph": "X", "name": "ApplyDefaultMarshalAsAttributeVisitor in assembly", "args": { "durationMS": 0.404599994421005, "detail": "Assembly-CSharp" } },
{ "pid": 1, "tid": 1, "ts": 774732.788085938, "dur": 14686.3012313843, "ph": "X", "name": "WriteResources", "args": { "durationMS": 14.6863012313843, "detail": "" } },
{ "pid": 1, "tid": 1, "ts": 789715.515136719, "dur": 1298181.03027344, "ph": "X", "name": "CopyEtcFolder", "args": { "durationMS": 1298.18103027344, "detail": "" } },
{ "pid": 1, "tid": 1, "ts": 2088851.07421875, "dur": 355597.381591797, "ph": "X", "name": "PreProcessStage", "args": { "durationMS": 355.597381591797, "detail": "" } },
{ "pid": 1, "tid": 1, "ts": 2444454.58984375, "dur": 5623.70014190674, "ph": "X", "name": "Debugger Sequence Points", "args": { "durationMS": 5.62370014190674, "detail": "" } },
{ "pid": 1, "tid": 1, "ts": 2451791.74804688, "dur": 1934866.45507813, "ph": "X", "name": "Generics Collection", "args": { "durationMS": 1934.86645507813, "detail": "" } },
{ "pid": 1, "tid": 1, "ts": 2451792.48046875, "dur": 1924020.38574219, "ph": "X", "name": "GenericsCollector.Collect", "args": { "durationMS": 1924.02038574219, "detail": "" } },
{ "pid": 1, "tid": 1, "ts": 4375812.98828125, "dur": 7626.2001991272, "ph": "X", "name": "CollectGenericVirtualMethods.Collect", "args": { "durationMS": 7.6262001991272, "detail": "" } },
{ "pid": 1, "tid": 1, "ts": 4383439.453125, "dur": 2791.80002212524, "ph": "X", "name": "AddExtraTypes", "args": { "durationMS": 2.79180002212524, "detail": "" } },
{ "pid": 1, "tid": 1, "ts": 4386658.203125, "dur": 2413.00010681152, "ph": "X", "name": "Add Windows Runtime type names", "args": { "durationMS": 2.41300010681152, "detail": "" } },
{ "pid": 1, "tid": 1, "ts": 4386658.203125, "dur": 2411.99994087219, "ph": "X", "name": "Add Windows Runtime type names", "args": { "durationMS": 2.41199994087219, "detail": "" } },
{ "pid": 1, "tid": 1, "ts": 4501480.46875, "dur": 9142080.078125, "ph": "X", "name": "AllAssemblyConversion", "args": { "durationMS": 9142.080078125, "detail": "" } },
{ "pid": 1, "tid": 1, "ts": 4507986.81640625, "dur": 4750791.50390625, "ph": "X", "name": "Convert", "args": { "durationMS": 4750.79150390625, "detail": "mscorlib" } },
{ "pid": 1, "tid": 1, "ts": 4507990.234375, "dur": 4750787.59765625, "ph": "X", "name": "Code", "args": { "durationMS": 4750.78759765625, "detail": "" } },
{ "pid": 1, "tid": 1, "ts": 4508796.875, "dur": 4749979.98046875, "ph": "X", "name": "Methods", "args": { "durationMS": 4749.97998046875, "detail": "Definitions" } },
{ "pid": 1, "tid": 1, "ts": 9264444.3359375, "dur": 833091.125488281, "ph": "X", "name": "Convert", "args": { "durationMS": 833.091125488281, "detail": "System" } },
{ "pid": 1, "tid": 1, "ts": 9264448.2421875, "dur": 833086.9140625, "ph": "X", "name": "Code", "args": { "durationMS": 833.0869140625, "detail": "" } },
{ "pid": 1, "tid": 1, "ts": 9264503.90625, "dur": 833030.395507813, "ph": "X", "name": "Methods", "args": { "durationMS": 833.030395507813, "detail": "Definitions" } },
{ "pid": 1, "tid": 1, "ts": 10118520.5078125, "dur": 69627.9983520508, "ph": "X", "name": "Convert", "args": { "durationMS": 69.6279983520508, "detail": "Mono.Security" } },
{ "pid": 1, "tid": 1, "ts": 10118526.3671875, "dur": 69622.5967407227, "ph": "X", "name": "Code", "args": { "durationMS": 69.6225967407227, "detail": "" } },
{ "pid": 1, "tid": 1, "ts": 10118620.1171875, "dur": 69528.0990600586, "ph": "X", "name": "Methods", "args": { "durationMS": 69.5280990600586, "detail": "Definitions" } },
{ "pid": 1, "tid": 1, "ts": 10198501.953125, "dur": 25766.300201416, "ph": "X", "name": "Convert", "args": { "durationMS": 25.766300201416, "detail": "System.Xml" } },
{ "pid": 1, "tid": 1, "ts": 10198505.859375, "dur": 25761.8999481201, "ph": "X", "name": "Code", "args": { "durationMS": 25.7618999481201, "detail": "" } },
{ "pid": 1, "tid": 1, "ts": 10198512.6953125, "dur": 25753.999710083, "ph": "X", "name": "Methods", "args": { "durationMS": 25.753999710083, "detail": "Definitions" } },
{ "pid": 1, "tid": 1, "ts": 10240805.6640625, "dur": 37427.5016784668, "ph": "X", "name": "Convert", "args": { "durationMS": 37.4275016784668, "detail": "System.Configuration" } },
{ "pid": 1, "tid": 1, "ts": 10240810.546875, "dur": 37423.2978820801, "ph": "X", "name": "Code", "args": { "durationMS": 37.4232978820801, "detail": "" } },
{ "pid": 1, "tid": 1, "ts": 10240821.2890625, "dur": 37411.4990234375, "ph": "X", "name": "Methods", "args": { "durationMS": 37.4114990234375, "detail": "Definitions" } },
{ "pid": 1, "tid": 1, "ts": 10287333.0078125, "dur": 16276.5998840332, "ph": "X", "name": "Convert", "args": { "durationMS": 16.2765998840332, "detail": "System.Core" } },
{ "pid": 1, "tid": 1, "ts": 10287336.9140625, "dur": 16272.0985412598, "ph": "X", "name": "Code", "args": { "durationMS": 16.2720985412598, "detail": "" } },
{ "pid": 1, "tid": 1, "ts": 10287347.65625, "dur": 16260.3015899658, "ph": "X", "name": "Methods", "args": { "durationMS": 16.2603015899658, "detail": "Definitions" } },
{ "pid": 1, "tid": 1, "ts": 10308765.625, "dur": 30594.9001312256, "ph": "X", "name": "Convert", "args": { "durationMS": 30.5949001312256, "detail": "UnityEngine.SharedInternalsModule" } },
{ "pid": 1, "tid": 1, "ts": 10308770.5078125, "dur": 30590.5990600586, "ph": "X", "name": "Code", "args": { "durationMS": 30.5905990600586, "detail": "" } },
{ "pid": 1, "tid": 1, "ts": 10308782.2265625, "dur": 30577.6996612549, "ph": "X", "name": "Methods", "args": { "durationMS": 30.5776996612549, "detail": "Definitions" } },
{ "pid": 1, "tid": 1, "ts": 10346709.9609375, "dur": 822493.103027344, "ph": "X", "name": "Convert", "args": { "durationMS": 822.493103027344, "detail": "UnityEngine.CoreModule" } },
{ "pid": 1, "tid": 1, "ts": 10346713.8671875, "dur": 822489.013671875, "ph": "X", "name": "Code", "args": { "durationMS": 822.489013671875, "detail": "" } },
{ "pid": 1, "tid": 1, "ts": 10346855.46875, "dur": 822346.618652344, "ph": "X", "name": "Methods", "args": { "durationMS": 822.346618652344, "detail": "Definitions" } },
{ "pid": 1, "tid": 1, "ts": 11173896.484375, "dur": 8056.0998916626, "ph": "X", "name": "Convert", "args": { "durationMS": 8.0560998916626, "detail": "System.Diagnostics.StackTrace" } },
{ "pid": 1, "tid": 1, "ts": 11173899.4140625, "dur": 8052.59990692139, "ph": "X", "name": "Code", "args": { "durationMS": 8.05259990692139, "detail": "" } },
{ "pid": 1, "tid": 1, "ts": 11173904.296875, "dur": 8046.89979553223, "ph": "X", "name": "Methods", "args": { "durationMS": 8.04689979553223, "detail": "Definitions" } },
{ "pid": 1, "tid": 1, "ts": 11188775.390625, "dur": 8723.4001159668, "ph": "X", "name": "Convert", "args": { "durationMS": 8.7234001159668, "detail": "System.Globalization.Extensions" } },
{ "pid": 1, "tid": 1, "ts": 11188779.296875, "dur": 8719.30027008057, "ph": "X", "name": "Code", "args": { "durationMS": 8.71930027008057, "detail": "" } },
{ "pid": 1, "tid": 1, "ts": 11188785.15625, "dur": 8713.39988708496, "ph": "X", "name": "Methods", "args": { "durationMS": 8.71339988708496, "detail": "Definitions" } },
{ "pid": 1, "tid": 1, "ts": 11205136.71875, "dur": 38744.0986633301, "ph": "X", "name": "Convert", "args": { "durationMS": 38.7440986633301, "detail": "UnityEngine.TextRenderingModule" } },
{ "pid": 1, "tid": 1, "ts": 11205139.6484375, "dur": 38739.9024963379, "ph": "X", "name": "Code", "args": { "durationMS": 38.7399024963379, "detail": "" } },
{ "pid": 1, "tid": 1, "ts": 11205148.4375, "dur": 38730.598449707, "ph": "X", "name": "Methods", "args": { "durationMS": 38.730598449707, "detail": "Definitions" } },
{ "pid": 1, "tid": 1, "ts": 11248742.1875, "dur": 51195.2018737793, "ph": "X", "name": "Convert", "args": { "durationMS": 51.1952018737793, "detail": "UnityEngine.AnimationModule" } },
{ "pid": 1, "tid": 1, "ts": 11248746.09375, "dur": 51191.6999816895, "ph": "X", "name": "Code", "args": { "durationMS": 51.1916999816895, "detail": "" } },
{ "pid": 1, "tid": 1, "ts": 11248759.765625, "dur": 51177.2994995117, "ph": "X", "name": "Methods", "args": { "durationMS": 51.1772994995117, "detail": "Definitions" } },
{ "pid": 1, "tid": 1, "ts": 11306186.5234375, "dur": 107221.000671387, "ph": "X", "name": "Convert", "args": { "durationMS": 107.221000671387, "detail": "UnityEngine.IMGUIModule" } },
{ "pid": 1, "tid": 1, "ts": 11306189.453125, "dur": 107217.597961426, "ph": "X", "name": "Code", "args": { "durationMS": 107.217597961426, "detail": "" } },
{ "pid": 1, "tid": 1, "ts": 11306203.125, "dur": 107203.804016113, "ph": "X", "name": "Methods", "args": { "durationMS": 107.203804016113, "detail": "Definitions" } },
{ "pid": 1, "tid": 1, "ts": 11419035.15625, "dur": 33222.8012084961, "ph": "X", "name": "Convert", "args": { "durationMS": 33.2228012084961, "detail": "UnityEngine.InputLegacyModule" } },
{ "pid": 1, "tid": 1, "ts": 11419039.0625, "dur": 33218.4982299805, "ph": "X", "name": "Code", "args": { "durationMS": 33.2184982299805, "detail": "" } },
{ "pid": 1, "tid": 1, "ts": 11419047.8515625, "dur": 33210.2012634277, "ph": "X", "name": "Methods", "args": { "durationMS": 33.2102012634277, "detail": "Definitions" } },
{ "pid": 1, "tid": 1, "ts": 11458985.3515625, "dur": 32873.7983703613, "ph": "X", "name": "Convert", "args": { "durationMS": 32.8737983703613, "detail": "UnityEngine.Physics2DModule" } },
{ "pid": 1, "tid": 1, "ts": 11458988.28125, "dur": 32870.2011108398, "ph": "X", "name": "Code", "args": { "durationMS": 32.8702011108398, "detail": "" } },
{ "pid": 1, "tid": 1, "ts": 11458997.0703125, "dur": 32861.2976074219, "ph": "X", "name": "Methods", "args": { "durationMS": 32.8612976074219, "detail": "Definitions" } },
{ "pid": 1, "tid": 1, "ts": 11496839.84375, "dur": 12017.1003341675, "ph": "X", "name": "Convert", "args": { "durationMS": 12.0171003341675, "detail": "UnityEngine.PhysicsModule" } },
{ "pid": 1, "tid": 1, "ts": 11496841.796875, "dur": 12013.6003494263, "ph": "X", "name": "Code", "args": { "durationMS": 12.0136003494263, "detail": "" } },
{ "pid": 1, "tid": 1, "ts": 11496848.6328125, "dur": 12006.8998336792, "ph": "X", "name": "Methods", "args": { "durationMS": 12.0068998336792, "detail": "Definitions" } },
{ "pid": 1, "tid": 1, "ts": 11513297.8515625, "dur": 39502.2010803223, "ph": "X", "name": "Convert", "args": { "durationMS": 39.5022010803223, "detail": "UnityEngine.UIModule" } },
{ "pid": 1, "tid": 1, "ts": 11513301.7578125, "dur": 39498.6991882324, "ph": "X", "name": "Code", "args": { "durationMS": 39.4986991882324, "detail": "" } },
{ "pid": 1, "tid": 1, "ts": 11513312.5, "dur": 39486.701965332, "ph": "X", "name": "Methods", "args": { "durationMS": 39.486701965332, "detail": "Definitions" } },
{ "pid": 1, "tid": 1, "ts": 11557229.4921875, "dur": 12989.9997711182, "ph": "X", "name": "Convert", "args": { "durationMS": 12.9899997711182, "detail": "netstandard" } },
{ "pid": 1, "tid": 1, "ts": 11557232.421875, "dur": 12986.3004684448, "ph": "X", "name": "Code", "args": { "durationMS": 12.9863004684448, "detail": "" } },
{ "pid": 1, "tid": 1, "ts": 11557238.28125, "dur": 12979.9003601074, "ph": "X", "name": "Methods", "args": { "durationMS": 12.9799003601074, "detail": "Definitions" } },
{ "pid": 1, "tid": 1, "ts": 11575081.0546875, "dur": 20275.1007080078, "ph": "X", "name": "Convert", "args": { "durationMS": 20.2751007080078, "detail": "UnityEngine.AudioModule" } },
{ "pid": 1, "tid": 1, "ts": 11575084.9609375, "dur": 20271.6007232666, "ph": "X", "name": "Code", "args": { "durationMS": 20.2716007232666, "detail": "" } },
{ "pid": 1, "tid": 1, "ts": 11575095.703125, "dur": 20260.9996795654, "ph": "X", "name": "Methods", "args": { "durationMS": 20.2609996795654, "detail": "Definitions" } },
{ "pid": 1, "tid": 1, "ts": 11602125.9765625, "dur": 10732.8996658325, "ph": "X", "name": "Convert", "args": { "durationMS": 10.7328996658325, "detail": "UnityEngine.ImageConversionModule" } },
{ "pid": 1, "tid": 1, "ts": 11602129.8828125, "dur": 10728.6996841431, "ph": "X", "name": "Code", "args": { "durationMS": 10.7286996841431, "detail": "" } },
{ "pid": 1, "tid": 1, "ts": 11602136.71875, "dur": 10721.7998504639, "ph": "X", "name": "Methods", "args": { "durationMS": 10.7217998504639, "detail": "Definitions" } },
{ "pid": 1, "tid": 1, "ts": 11620834.9609375, "dur": 1230862.91503906, "ph": "X", "name": "Convert", "args": { "durationMS": 1230.86291503906, "detail": "UnityEngine.UI" } },
{ "pid": 1, "tid": 1, "ts": 11620839.84375, "dur": 1230858.15429688, "ph": "X", "name": "Code", "args": { "durationMS": 1230.85815429688, "detail": "" } },
{ "pid": 1, "tid": 1, "ts": 11620916.015625, "dur": 1230782.2265625, "ph": "X", "name": "Methods", "args": { "durationMS": 1230.7822265625, "detail": "Definitions" } },
{ "pid": 1, "tid": 1, "ts": 12856179.6875, "dur": 19306.0989379883, "ph": "X", "name": "Convert", "args": { "durationMS": 19.3060989379883, "detail": "LeanCommon" } },
{ "pid": 1, "tid": 1, "ts": 12856183.59375, "dur": 19302.6008605957, "ph": "X", "name": "Code", "args": { "durationMS": 19.3026008605957, "detail": "" } },
{ "pid": 1, "tid": 1, "ts": 12856190.4296875, "dur": 19294.8989868164, "ph": "X", "name": "Methods", "args": { "durationMS": 19.2948989868164, "detail": "Definitions" } },
{ "pid": 1, "tid": 1, "ts": 12880409.1796875, "dur": 263753.509521484, "ph": "X", "name": "Convert", "args": { "durationMS": 263.753509521484, "detail": "LeanTransition" } },
{ "pid": 1, "tid": 1, "ts": 12880413.0859375, "dur": 263750.183105469, "ph": "X", "name": "Code", "args": { "durationMS": 263.750183105469, "detail": "" } },
{ "pid": 1, "tid": 1, "ts": 12880452.1484375, "dur": 263710.296630859, "ph": "X", "name": "Methods", "args": { "durationMS": 263.710296630859, "detail": "Definitions" } },
{ "pid": 1, "tid": 1, "ts": 13150508.7890625, "dur": 51397.3999023438, "ph": "X", "name": "Convert", "args": { "durationMS": 51.3973999023438, "detail": "UnityEngine.UnityWebRequestModule" } },
{ "pid": 1, "tid": 1, "ts": 13150512.6953125, "dur": 51393.2991027832, "ph": "X", "name": "Code", "args": { "durationMS": 51.3932991027832, "detail": "" } },
{ "pid": 1, "tid": 1, "ts": 13150521.484375, "dur": 51383.6975097656, "ph": "X", "name": "Methods", "args": { "durationMS": 51.3836975097656, "detail": "Definitions" } },
{ "pid": 1, "tid": 1, "ts": 13206289.0625, "dur": 169960.403442383, "ph": "X", "name": "Convert", "args": { "durationMS": 169.960403442383, "detail": "LeanGUI" } },
{ "pid": 1, "tid": 1, "ts": 13206292.96875, "dur": 169957.000732422, "ph": "X", "name": "Code", "args": { "durationMS": 169.957000732422, "detail": "" } },
{ "pid": 1, "tid": 1, "ts": 13206307.6171875, "dur": 169940.902709961, "ph": "X", "name": "Methods", "args": { "durationMS": 169.940902709961, "detail": "Definitions" } },
{ "pid": 1, "tid": 1, "ts": 13381001.953125, "dur": 17889.9002075195, "ph": "X", "name": "Convert", "args": { "durationMS": 17.8899002075195, "detail": "UnityEngine.UnityAnalyticsModule" } },
{ "pid": 1, "tid": 1, "ts": 13381004.8828125, "dur": 17886.3010406494, "ph": "X", "name": "Code", "args": { "durationMS": 17.8863010406494, "detail": "" } },
{ "pid": 1, "tid": 1, "ts": 13381013.671875, "dur": 17877.799987793, "ph": "X", "name": "Methods", "args": { "durationMS": 17.877799987793, "detail": "Definitions" } },
{ "pid": 1, "tid": 1, "ts": 13405102.5390625, "dur": 13507.5998306274, "ph": "X", "name": "Convert", "args": { "durationMS": 13.5075998306274, "detail": "UnityEngine.UnityWebRequestWWWModule" } },
{ "pid": 1, "tid": 1, "ts": 13405106.4453125, "dur": 13503.8003921509, "ph": "X", "name": "Code", "args": { "durationMS": 13.5038003921509, "detail": "" } },
{ "pid": 1, "tid": 1, "ts": 13405112.3046875, "dur": 13497.1008300781, "ph": "X", "name": "Methods", "args": { "durationMS": 13.4971008300781, "detail": "Definitions" } },
{ "pid": 1, "tid": 1, "ts": 13423873.046875, "dur": 11282.2999954224, "ph": "X", "name": "Convert", "args": { "durationMS": 11.2822999954224, "detail": "UnityEngine" } },
{ "pid": 1, "tid": 1, "ts": 13423876.953125, "dur": 11278.5997390747, "ph": "X", "name": "Code", "args": { "durationMS": 11.2785997390747, "detail": "" } },
{ "pid": 1, "tid": 1, "ts": 13423882.8125, "dur": 11272.3999023438, "ph": "X", "name": "Methods", "args": { "durationMS": 11.2723999023438, "detail": "Definitions" } },
{ "pid": 1, "tid": 1, "ts": 13439981.4453125, "dur": 203568.603515625, "ph": "X", "name": "Convert", "args": { "durationMS": 203.568603515625, "detail": "Assembly-CSharp" } },
{ "pid": 1, "tid": 1, "ts": 13439985.3515625, "dur": 203564.895629883, "ph": "X", "name": "Code", "args": { "durationMS": 203.564895629883, "detail": "" } },
{ "pid": 1, "tid": 1, "ts": 13440004.8828125, "dur": 203545.104980469, "ph": "X", "name": "Methods", "args": { "durationMS": 203.545104980469, "detail": "Definitions" } },
{ "pid": 1, "tid": 1, "ts": 13643559.5703125, "dur": 5184458.984375, "ph": "X", "name": "WriteGenerics", "args": { "durationMS": 5184.458984375, "detail": "" } },
{ "pid": 1, "tid": 1, "ts": 13653854.4921875, "dur": 14192.6002502441, "ph": "X", "name": "Arrays Definitions", "args": { "durationMS": 14.1926002502441, "detail": "" } },
{ "pid": 1, "tid": 1, "ts": 13668799.8046875, "dur": 1324423.21777344, "ph": "X", "name": "GenericInstanceMethods", "args": { "durationMS": 1324.42321777344, "detail": "" } },
{ "pid": 1, "tid": 1, "ts": 14993224.609375, "dur": 3378098.87695313, "ph": "X", "name": "GenericInstanceTypes", "args": { "durationMS": 3378.09887695313, "detail": "" } },
{ "pid": 1, "tid": 1, "ts": 18371689.453125, "dur": 456239.624023438, "ph": "X", "name": "GenericComDefinitions", "args": { "durationMS": 456.239624023438, "detail": "" } },
{ "pid": 1, "tid": 1, "ts": 18837306.640625, "dur": 425.09999871254, "ph": "X", "name": "Executable Processing", "args": { "durationMS": 0.42509999871254, "detail": "" } },
{ "pid": 1, "tid": 1, "ts": 18844013.671875, "dur": 373217.590332031, "ph": "X", "name": "MetadataCollector", "args": { "durationMS": 373.217590332031, "detail": "" } },
{ "pid": 1, "tid": 1, "ts": 18847253.90625, "dur": 15818.7007904053, "ph": "X", "name": "UpdateEmptyTokens", "args": { "durationMS": 15.8187007904053, "detail": "" } },
{ "pid": 1, "tid": 1, "ts": 18865957.03125, "dur": 18044.8989868164, "ph": "X", "name": "ValidateTokens", "args": { "durationMS": 18.0448989868164, "detail": "" } },
{ "pid": 1, "tid": 1, "ts": 19217697.265625, "dur": 10367.3000335693, "ph": "X", "name": "Write COM Callable Wrappers", "args": { "durationMS": 10.3673000335693, "detail": "" } },
{ "pid": 1, "tid": 1, "ts": 19227529.296875, "dur": 534.099996089935, "ph": "X", "name": "Collect implemented projected interfaces by COM Callable Wrappers", "args": { "durationMS": 0.534099996089935, "detail": "" } },
{ "pid": 1, "tid": 1, "ts": 19228064.453125, "dur": 4140956.0546875, "ph": "X", "name": "Metadata", "args": { "durationMS": 4140.9560546875, "detail": "Global" } },
{ "pid": 1, "tid": 1, "ts": 19337958.984375, "dur": 645229.736328125, "ph": "X", "name": "Attributes", "args": { "durationMS": 645.229736328125, "detail": "" } },
{ "pid": 1, "tid": 1, "ts": 20199351.5625, "dur": 1121239.50195313, "ph": "X", "name": "WriteCodeRegistration", "args": { "durationMS": 1121.23950195313, "detail": "" } },
{ "pid": 1, "tid": 1, "ts": 20270236.328125, "dur": 7796.70000076294, "ph": "X", "name": "GenericContextCollector", "args": { "durationMS": 7.79670000076294, "detail": "Collect" } },
{ "pid": 1, "tid": 1, "ts": 20555468.75, "dur": 527.599990367889, "ph": "X", "name": "GenericContextCollector", "args": { "durationMS": 0.527599990367889, "detail": "Collect" } },
{ "pid": 1, "tid": 1, "ts": 21028339.84375, "dur": 19081.600189209, "ph": "X", "name": "ReversePInvokerWrapperTable", "args": { "durationMS": 19.081600189209, "detail": "Il2CppReversePInvokeWrapperTable.cpp" } },
{ "pid": 1, "tid": 1, "ts": 21048048.828125, "dur": 115945.892333984, "ph": "X", "name": "GenericMethodPointerTable", "args": { "durationMS": 115.945892333984, "detail": "Il2CppGenericMethodPointerTable.cpp" } },
{ "pid": 1, "tid": 1, "ts": 21164371.09375, "dur": 108643.905639648, "ph": "X", "name": "InvokerTable", "args": { "durationMS": 108.643905639648, "detail": "Il2CppInvokerTable.cpp" } },
{ "pid": 1, "tid": 1, "ts": 21275250, "dur": 29288.8984680176, "ph": "X", "name": "InteropDataTable", "args": { "durationMS": 29.2888984680176, "detail": "Il2CppInteropDataTable.cpp" } },
{ "pid": 1, "tid": 1, "ts": 21320591.796875, "dur": 2048426.51367188, "ph": "X", "name": "WriteMetadata", "args": { "durationMS": 2048.42651367188, "detail": "" } },
{ "pid": 1, "tid": 1, "ts": 21435312.5, "dur": 6366.19997024536, "ph": "X", "name": "Metadata", "args": { "durationMS": 6.36619997024536, "detail": "Collect string literals" } },
{ "pid": 1, "tid": 1, "ts": 21578914.0625, "dur": 145893.005371094, "ph": "X", "name": "GenericClasses", "args": { "durationMS": 145.893005371094, "detail": "" } },
{ "pid": 1, "tid": 1, "ts": 21724808.59375, "dur": 46327.8007507324, "ph": "X", "name": "GenericInst2", "args": { "durationMS": 46.3278007507324, "detail": "" } },
{ "pid": 1, "tid": 1, "ts": 21771136.71875, "dur": 352307.800292969, "ph": "X", "name": "GenericMethods", "args": { "durationMS": 352.307800292969, "detail": "" } },
{ "pid": 1, "tid": 1, "ts": 22123445.3125, "dur": 189441.207885742, "ph": "X", "name": "Il2CppTypes", "args": { "durationMS": 189.441207885742, "detail": "" } },
{ "pid": 1, "tid": 1, "ts": 22312886.71875, "dur": 78183.5021972656, "ph": "X", "name": "GenericMethods", "args": { "durationMS": 78.1835021972656, "detail": "" } },
{ "pid": 1, "tid": 1, "ts": 22391072.265625, "dur": 648777.770996094, "ph": "X", "name": "CompilerCalculateTypeValues", "args": { "durationMS": 648.777770996094, "detail": "" } },
{ "pid": 1, "tid": 1, "ts": 23039851.5625, "dur": 21890.6002044678, "ph": "X", "name": "Registration", "args": { "durationMS": 21.8906002044678, "detail": "" } },
{ "pid": 1, "tid": 1, "ts": 23117960.9375, "dur": 10000.3004074097, "ph": "X", "name": "StringLiteralWriter", "args": { "durationMS": 10.0003004074097, "detail": "" } },
{ "pid": 1, "tid": 1, "ts": 23128384.765625, "dur": 4147.99976348877, "ph": "X", "name": "Metadata Strings", "args": { "durationMS": 4.14799976348877, "detail": "" } },
{ "pid": 1, "tid": 1, "ts": 23132539.0625, "dur": 6058.49981307983, "ph": "X", "name": "Events", "args": { "durationMS": 6.05849981307983, "detail": "" } },
{ "pid": 1, "tid": 1, "ts": 23138599.609375, "dur": 7466.19987487793, "ph": "X", "name": "Properties", "args": { "durationMS": 7.46619987487793, "detail": "" } },
{ "pid": 1, "tid": 1, "ts": 23146064.453125, "dur": 102909.194946289, "ph": "X", "name": "Methods", "args": { "durationMS": 102.909194946289, "detail": "" } },
{ "pid": 1, "tid": 1, "ts": 23248976.5625, "dur": 2871.29998207092, "ph": "X", "name": "Parameter Default Values", "args": { "durationMS": 2.87129998207092, "detail": "" } },
{ "pid": 1, "tid": 1, "ts": 23251847.65625, "dur": 3152.89998054504, "ph": "X", "name": "Field Default Values", "args": { "durationMS": 3.15289998054504, "detail": "" } },
{ "pid": 1, "tid": 1, "ts": 23255001.953125, "dur": 633.199989795685, "ph": "X", "name": "Field and Parameter Default Values Data", "args": { "durationMS": 0.633199989795685, "detail": "" } },
{ "pid": 1, "tid": 1, "ts": 23255636.71875, "dur": 865.199983119965, "ph": "X", "name": "Field Marshaled Sizes", "args": { "durationMS": 0.865199983119965, "detail": "" } },
{ "pid": 1, "tid": 1, "ts": 23256503.90625, "dur": 16004.9991607666, "ph": "X", "name": "Parameters", "args": { "durationMS": 16.0049991607666, "detail": "" } },
{ "pid": 1, "tid": 1, "ts": 23272507.8125, "dur": 9254.19998168945, "ph": "X", "name": "Fields", "args": { "durationMS": 9.25419998168945, "detail": "" } },
{ "pid": 1, "tid": 1, "ts": 23281763.671875, "dur": 3083.69994163513, "ph": "X", "name": "Generic Parameters", "args": { "durationMS": 3.08369994163513, "detail": "" } },
{ "pid": 1, "tid": 1, "ts": 23284847.65625, "dur": 1509.09996032715, "ph": "X", "name": "Generic Parameter Constraints", "args": { "durationMS": 1.50909996032715, "detail": "" } },
{ "pid": 1, "tid": 1, "ts": 23286357.421875, "dur": 1875.3000497818, "ph": "X", "name": "Generic Containers", "args": { "durationMS": 1.8753000497818, "detail": "" } },
{ "pid": 1, "tid": 1, "ts": 23288234.375, "dur": 498.400002717972, "ph": "X", "name": "Nested Types", "args": { "durationMS": 0.498400002717972, "detail": "" } },
{ "pid": 1, "tid": 1, "ts": 23288732.421875, "dur": 466.800004243851, "ph": "X", "name": "Interfaces", "args": { "durationMS": 0.466800004243851, "detail": "" } },
{ "pid": 1, "tid": 1, "ts": 23289201.171875, "dur": 2272.39990234375, "ph": "X", "name": "VTables", "args": { "durationMS": 2.27239990234375, "detail": "" } },
{ "pid": 1, "tid": 1, "ts": 23291470.703125, "dur": 1608.29997062683, "ph": "X", "name": "Interface Offsets", "args": { "durationMS": 1.60829997062683, "detail": "" } },
{ "pid": 1, "tid": 1, "ts": 23293082.03125, "dur": 51826.7021179199, "ph": "X", "name": "Type Definitions", "args": { "durationMS": 51.8267021179199, "detail": "" } },
{ "pid": 1, "tid": 1, "ts": 23344910.15625, "dur": 5264.90020751953, "ph": "X", "name": "Images", "args": { "durationMS": 5.26490020751953, "detail": "" } },
{ "pid": 1, "tid": 1, "ts": 23350173.828125, "dur": 3555.0000667572, "ph": "X", "name": "Assemblies", "args": { "durationMS": 3.5550000667572, "detail": "" } },
{ "pid": 1, "tid": 1, "ts": 23353730.46875, "dur": 2651.40008926392, "ph": "X", "name": "Metadata Usage Lists", "args": { "durationMS": 2.65140008926392, "detail": "" } },
{ "pid": 1, "tid": 1, "ts": 23356382.8125, "dur": 1936.90001964569, "ph": "X", "name": "Metadata Usage Pairs", "args": { "durationMS": 1.93690001964569, "detail": "" } },
{ "pid": 1, "tid": 1, "ts": 23358322.265625, "dur": 400.099992752075, "ph": "X", "name": "Field Refs", "args": { "durationMS": 0.400099992752075, "detail": "" } },
{ "pid": 1, "tid": 1, "ts": 23358720.703125, "dur": 560.400009155273, "ph": "X", "name": "Referenced Assemblies", "args": { "durationMS": 0.560400009155273, "detail": "" } },
{ "pid": 1, "tid": 1, "ts": 23359283.203125, "dur": 1631.39998912811, "ph": "X", "name": "Attribute Types Ranges", "args": { "durationMS": 1.63139998912811, "detail": "" } },
{ "pid": 1, "tid": 1, "ts": 23360916.015625, "dur": 1045.09997367859, "ph": "X", "name": "Attribute Types", "args": { "durationMS": 1.04509997367859, "detail": "" } },
{ "pid": 1, "tid": 1, "ts": 23361960.9375, "dur": 454.800009727478, "ph": "X", "name": "Unresolved Virtual Call Parameter Types", "args": { "durationMS": 0.454800009727478, "detail": "" } },
{ "pid": 1, "tid": 1, "ts": 23362416.015625, "dur": 1385.20002365112, "ph": "X", "name": "Unresolved Virtual Call Parameter Ranges", "args": { "durationMS": 1.38520002365112, "detail": "" } },
{ "pid": 1, "tid": 1, "ts": 23363802.734375, "dur": 697.899997234344, "ph": "X", "name": "Windows Runtime type names", "args": { "durationMS": 0.697899997234344, "detail": "" } },
{ "pid": 1, "tid": 1, "ts": 23364500, "dur": 2316.80011749268, "ph": "X", "name": "Exported Types", "args": { "durationMS": 2.31680011749268, "detail": "" } },
{ "pid": 1, "tid": 1, "ts": 24190080.078125, "dur": 96630515.625, "ph": "X", "name": "Build", "args": { "durationMS": 96630.515625, "detail": "" } },
{ "pid": 1, "tid": 1, "ts": 24195056.640625, "dur": 96604562.5, "ph": "X", "name": "BuildBinary", "args": { "durationMS": 96604.5625, "detail": "" } },
{ "pid": 1, "tid": 1, "ts": 24195337.890625, "dur": 345288.604736328, "ph": "X", "name": "FindFilesToCompile", "args": { "durationMS": 345.288604736328, "detail": "" } },
{ "pid": 1, "tid": 1, "ts": 24540626.953125, "dur": 5485375, "ph": "X", "name": "Calculate header hashes", "args": { "durationMS": 5485.375, "detail": "" } },
{ "pid": 1, "tid": 1, "ts": 24544140.625, "dur": 4211670.8984375, "ph": "X", "name": "HashOfAllFilesWithProviderExtensionInDirectory", "args": { "durationMS": 4211.6708984375, "detail": "D:\\Program Files\\Unity\\Install\\2019.2.13f1\\Editor\\Data\\il2cpp\\libil2cpp" } },
{ "pid": 1, "tid": 1, "ts": 28755949.21875, "dur": 485110.473632813, "ph": "X", "name": "HashOfAllFilesWithProviderExtensionInDirectory", "args": { "durationMS": 485.110473632813, "detail": "D:\\Program Files\\Unity\\Install\\2019.2.13f1\\Editor\\Data\\il2cpp\\external\\bdwgc\\include" } },
{ "pid": 1, "tid": 1, "ts": 29241111.328125, "dur": 39741.2986755371, "ph": "X", "name": "HashOfAllFilesWithProviderExtensionInDirectory", "args": { "durationMS": 39.7412986755371, "detail": "D:\\Program Files\\Unity\\Install\\2019.2.13f1\\Editor\\Data\\il2cpp\\external\\xxHash" } },
{ "pid": 1, "tid": 1, "ts": 29280908.203125, "dur": 2509.70005989075, "ph": "X", "name": "HashOfAllFilesWithProviderExtensionInDirectory", "args": { "durationMS": 2.50970005989075, "detail": "D:\\Documents\\Faks\\Diplomski Rad Prototiip\\WaterSystemPrototype\\Water System Prototype\\Temp\\StagingArea\\Data\\il2cppOutput" } },
{ "pid": 1, "tid": 1, "ts": 29292494.140625, "dur": 732274.597167969, "ph": "X", "name": "HashOfAllFilesWithProviderExtensionInDirectory", "args": { "durationMS": 732.274597167969, "detail": "D:\\Program Files\\Unity\\Install\\2019.2.13f1\\Editor\\Data\\il2cpp\\external\\bdwgc\\libatomic_ops\\src" } },
{ "pid": 1, "tid": 1, "ts": 30026003.90625, "dur": 5429681.15234375, "ph": "X", "name": "Calculate lumped hashes", "args": { "durationMS": 5429.68115234375, "detail": "" } },
{ "pid": 1, "tid": 1, "ts": 30027156.25, "dur": 31622.4994659424, "ph": "X", "name": "HashOfAllFilesWithProviderExtensionInDirectory", "args": { "durationMS": 31.6224994659424, "detail": "D:\\Program Files\\Unity\\Install\\2019.2.13f1\\Editor\\Data\\il2cpp\\libil2cpp\\codegen" } },
{ "pid": 1, "tid": 1, "ts": 30058826.171875, "dur": 8627.69985198975, "ph": "X", "name": "HashOfAllFilesWithProviderExtensionInDirectory", "args": { "durationMS": 8.62769985198975, "detail": "D:\\Program Files\\Unity\\Install\\2019.2.13f1\\Editor\\Data\\il2cpp\\libil2cpp\\debugger" } },
{ "pid": 1, "tid": 1, "ts": 30067500, "dur": 55565.1969909668, "ph": "X", "name": "HashOfAllFilesWithProviderExtensionInDirectory", "args": { "durationMS": 55.5651969909668, "detail": "D:\\Program Files\\Unity\\Install\\2019.2.13f1\\Editor\\Data\\il2cpp\\libil2cpp\\gc" } },
{ "pid": 1, "tid": 1, "ts": 30123140.625, "dur": 1531299.43847656, "ph": "X", "name": "HashOfAllFilesWithProviderExtensionInDirectory", "args": { "durationMS": 1531.29943847656, "detail": "D:\\Program Files\\Unity\\Install\\2019.2.13f1\\Editor\\Data\\il2cpp\\libil2cpp\\icalls" } },
{ "pid": 1, "tid": 1, "ts": 31654484.375, "dur": 174512.298583984, "ph": "X", "name": "HashOfAllFilesWithProviderExtensionInDirectory", "args": { "durationMS": 174.512298583984, "detail": "D:\\Program Files\\Unity\\Install\\2019.2.13f1\\Editor\\Data\\il2cpp\\libil2cpp\\metadata" } },
{ "pid": 1, "tid": 1, "ts": 31829095.703125, "dur": 83615.3945922852, "ph": "X", "name": "HashOfAllFilesWithProviderExtensionInDirectory", "args": { "durationMS": 83.6153945922852, "detail": "D:\\Program Files\\Unity\\Install\\2019.2.13f1\\Editor\\Data\\il2cpp\\libil2cpp\\mono" } },
{ "pid": 1, "tid": 1, "ts": 31912761.71875, "dur": 14681.4002990723, "ph": "X", "name": "HashOfAllFilesWithProviderExtensionInDirectory", "args": { "durationMS": 14.6814002990723, "detail": "D:\\Program Files\\Unity\\Install\\2019.2.13f1\\Editor\\Data\\il2cpp\\libil2cpp\\mono-runtime" } },
{ "pid": 1, "tid": 1, "ts": 31927490.234375, "dur": 1755017.21191406, "ph": "X", "name": "HashOfAllFilesWithProviderExtensionInDirectory", "args": { "durationMS": 1755.01721191406, "detail": "D:\\Program Files\\Unity\\Install\\2019.2.13f1\\Editor\\Data\\il2cpp\\libil2cpp\\os" } },
{ "pid": 1, "tid": 1, "ts": 33682558.59375, "dur": 139255.096435547, "ph": "X", "name": "HashOfAllFilesWithProviderExtensionInDirectory", "args": { "durationMS": 139.255096435547, "detail": "D:\\Program Files\\Unity\\Install\\2019.2.13f1\\Editor\\Data\\il2cpp\\libil2cpp\\utils" } },
{ "pid": 1, "tid": 1, "ts": 33821859.375, "dur": 556980.102539063, "ph": "X", "name": "HashOfAllFilesWithProviderExtensionInDirectory", "args": { "durationMS": 556.980102539063, "detail": "D:\\Program Files\\Unity\\Install\\2019.2.13f1\\Editor\\Data\\il2cpp\\libil2cpp\\vm" } },
{ "pid": 1, "tid": 1, "ts": 34378886.71875, "dur": 49891.9982910156, "ph": "X", "name": "HashOfAllFilesWithProviderExtensionInDirectory", "args": { "durationMS": 49.8919982910156, "detail": "D:\\Program Files\\Unity\\Install\\2019.2.13f1\\Editor\\Data\\il2cpp\\libil2cpp\\vm-utils" } },
{ "pid": 1, "tid": 1, "ts": 34428828.125, "dur": 1026846.55761719, "ph": "X", "name": "HashOfAllFilesWithProviderExtensionInDirectory", "args": { "durationMS": 1026.84655761719, "detail": "D:\\Program Files\\Unity\\Install\\2019.2.13f1\\Editor\\Data\\il2cpp\\external\\bdwgc" } },
{ "pid": 1, "tid": 1, "ts": 35455683.59375, "dur": 19890755.859375, "ph": "X", "name": "BuildAllCppFiles", "args": { "durationMS": 19890.755859375, "detail": "" } },
{ "pid": 1, "tid": 1, "ts": 35461371.09375, "dur": 19885068.359375, "ph": "X", "name": "Compile", "args": { "durationMS": 19885.068359375, "detail": "" } },
{ "pid": 1, "tid": 1, "ts": 55346441.40625, "dur": 736.599981784821, "ph": "X", "name": "OnBeforeLink Build", "args": { "durationMS": 0.736599981784821, "detail": "" } },
{ "pid": 1, "tid": 1, "ts": 55347183.59375, "dur": 63963222.65625, "ph": "X", "name": "Postprocess Object Files", "args": { "durationMS": 63963.22265625, "detail": "" } },
{ "pid": 1, "tid": 1, "ts": 55348960.9375, "dur": 63961433.59375, "ph": "X", "name": "Link", "args": { "durationMS": 63961.43359375, "detail": "build.bc" } },
{ "pid": 1, "tid": 1, "ts": 55373128.90625, "dur": 2849187.25585938, "ph": "X", "name": "hash linker invocation", "args": { "durationMS": 2849.18725585938, "detail": "" } },
{ "pid": 1, "tid": 1, "ts": 58292042.96875, "dur": 60836890.625, "ph": "X", "name": "ActualLinkerInvocation", "args": { "durationMS": 60836.890625, "detail": "build.bc" } },
{ "pid": 1, "tid": 1, "ts": 119310398.4375, "dur": 1424006.46972656, "ph": "X", "name": "ProgramDescription Finalize Build", "args": { "durationMS": 1424.00646972656, "detail": "" } },
{ "pid": 1, "tid": 1, "ts": 120734492.1875, "dur": 65126.2969970703, "ph": "X", "name": "Clean IL2CPP Cache", "args": { "durationMS": 65.1262969970703, "detail": "" } },
{ "pid": 1, "tid": 7, "ph": "M", "name": "thread_name", "args": { "name": "" } },
{ "pid": 1, "tid": 7, "ts": 35492625, "dur": 29911.2987518311, "ph": "X", "name": "HashCompilerInvocation", "args": { "durationMS": 29.9112987518311, "detail": "Il2CppMetadataUsage.c" } },
{ "pid": 1, "tid": 7, "ts": 35522695.3125, "dur": 8093.29986572266, "ph": "X", "name": "HashCompilerInvocation", "args": { "durationMS": 8.09329986572266, "detail": "Il2CppInvokerTable.cpp" } },
{ "pid": 1, "tid": 7, "ts": 35530921.875, "dur": 8306.59961700439, "ph": "X", "name": "HashCompilerInvocation", "args": { "durationMS": 8.30659961700439, "detail": "mscorlib9.cpp" } },
{ "pid": 1, "tid": 7, "ts": 35539421.875, "dur": 537994.079589844, "ph": "X", "name": "HashCompilerInvocation", "args": { "durationMS": 537.994079589844, "detail": "mscorlib.cpp" } },
{ "pid": 1, "tid": 7, "ts": 36077617.1875, "dur": 7384.79995727539, "ph": "X", "name": "HashCompilerInvocation", "args": { "durationMS": 7.38479995727539, "detail": "mscorlib7.cpp" } },
{ "pid": 1, "tid": 7, "ts": 36085566.40625, "dur": 401508.697509766, "ph": "X", "name": "HashCompilerInvocation", "args": { "durationMS": 401.508697509766, "detail": "mscorlib12.cpp" } },
{ "pid": 1, "tid": 7, "ts": 36487277.34375, "dur": 6719.60020065308, "ph": "X", "name": "HashCompilerInvocation", "args": { "durationMS": 6.71960020065308, "detail": "mscorlib6.cpp" } },
{ "pid": 1, "tid": 7, "ts": 36494171.875, "dur": 474472.717285156, "ph": "X", "name": "HashCompilerInvocation", "args": { "durationMS": 474.472717285156, "detail": "UnityEngine.UI2.cpp" } },
{ "pid": 1, "tid": 7, "ts": 36968980.46875, "dur": 228720.199584961, "ph": "X", "name": "HashCompilerInvocation", "args": { "durationMS": 228.720199584961, "detail": "UnityEngine.CoreModule.cpp" } },
{ "pid": 1, "tid": 7, "ts": 37197933.59375, "dur": 521257.751464844, "ph": "X", "name": "HashCompilerInvocation", "args": { "durationMS": 521.257751464844, "detail": "System.cpp" } },
{ "pid": 1, "tid": 7, "ts": 37719550.78125, "dur": 334453.399658203, "ph": "X", "name": "HashCompilerInvocation", "args": { "durationMS": 334.453399658203, "detail": "Generics5.cpp" } },
{ "pid": 1, "tid": 7, "ts": 38054218.75, "dur": 250585.601806641, "ph": "X", "name": "HashCompilerInvocation", "args": { "durationMS": 250.585601806641, "detail": "Generics3.cpp" } },
{ "pid": 1, "tid": 7, "ts": 38305085.9375, "dur": 240545.684814453, "ph": "X", "name": "HashCompilerInvocation", "args": { "durationMS": 240.545684814453, "detail": "Generics7.cpp" } },
{ "pid": 1, "tid": 7, "ts": 38545835.9375, "dur": 158561.401367188, "ph": "X", "name": "HashCompilerInvocation", "args": { "durationMS": 158.561401367188, "detail": "Generics10.cpp" } },
{ "pid": 1, "tid": 7, "ts": 38704824.21875, "dur": 175344.207763672, "ph": "X", "name": "HashCompilerInvocation", "args": { "durationMS": 175.344207763672, "detail": "Generics9.cpp" } },
{ "pid": 1, "tid": 7, "ts": 38880398.4375, "dur": 206004.699707031, "ph": "X", "name": "HashCompilerInvocation", "args": { "durationMS": 206.004699707031, "detail": "LeanGUI.cpp" } },
{ "pid": 1, "tid": 7, "ts": 39086578.125, "dur": 40787.5022888184, "ph": "X", "name": "HashCompilerInvocation", "args": { "durationMS": 40.7875022888184, "detail": "Il2CppCompilerCalculateTypeValuesTable.cpp" } },
{ "pid": 1, "tid": 7, "ts": 39127628.90625, "dur": 56501.1978149414, "ph": "X", "name": "HashCompilerInvocation", "args": { "durationMS": 56.5011978149414, "detail": "UnityEngine.CoreModule_CodeGen.c" } },
{ "pid": 1, "tid": 7, "ts": 39184335.9375, "dur": 152367.706298828, "ph": "X", "name": "HashCompilerInvocation", "args": { "durationMS": 152.367706298828, "detail": "UnityEngine.UIModule.cpp" } },
{ "pid": 1, "tid": 7, "ts": 39336925.78125, "dur": 75434.2956542969, "ph": "X", "name": "HashCompilerInvocation", "args": { "durationMS": 75.4342956542969, "detail": "UnityEngine.InputLegacyModule.cpp" } },
{ "pid": 1, "tid": 7, "ts": 39412562.5, "dur": 2288.59996795654, "ph": "X", "name": "HashCompilerInvocation", "args": { "durationMS": 2.28859996795654, "detail": "Il2CppInteropDataTable.cpp" } },
{ "pid": 1, "tid": 7, "ts": 39415058.59375, "dur": 92316.2002563477, "ph": "X", "name": "HashCompilerInvocation", "args": { "durationMS": 92.3162002563477, "detail": "UnityEngine.AudioModule.cpp" } },
{ "pid": 1, "tid": 7, "ts": 39507601.5625, "dur": 19734.8003387451, "ph": "X", "name": "HashCompilerInvocation", "args": { "durationMS": 19.7348003387451, "detail": "Assembly-CSharp_CodeGen.c" } },
{ "pid": 1, "tid": 7, "ts": 39527503.90625, "dur": 106707.000732422, "ph": "X", "name": "HashCompilerInvocation", "args": { "durationMS": 106.707000732422, "detail": "inflate.c" } },
{ "pid": 1, "tid": 7, "ts": 39634488.28125, "dur": 80818.1991577148, "ph": "X", "name": "HashCompilerInvocation", "args": { "durationMS": 80.8181991577148, "detail": "UnityEngine.PhysicsModule.cpp" } },
{ "pid": 1, "tid": 7, "ts": 39715503.90625, "dur": 1431.3999414444, "ph": "X", "name": "HashCompilerInvocation", "args": { "durationMS": 1.4313999414444, "detail": "Lump_libil2cpp_icalls.cpp" } },
{ "pid": 1, "tid": 7, "ts": 39717125, "dur": 509.400010108948, "ph": "X", "name": "HashCompilerInvocation", "args": { "durationMS": 0.509400010108948, "detail": "Lump_libil2cpp_os.cpp" } },
{ "pid": 1, "tid": 7, "ts": 39717785.15625, "dur": 40245.8992004395, "ph": "X", "name": "HashCompilerInvocation", "args": { "durationMS": 40.2458992004395, "detail": "gzwrite.c" } },
{ "pid": 1, "tid": 7, "ts": 39758234.375, "dur": 32662.59765625, "ph": "X", "name": "HashCompilerInvocation", "args": { "durationMS": 32.66259765625, "detail": "UnityEngine.TextRenderingModule_CodeGen.c" } },
{ "pid": 1, "tid": 7, "ts": 39791140.625, "dur": 926.800012588501, "ph": "X", "name": "HashCompilerInvocation", "args": { "durationMS": 0.926800012588501, "detail": "System.Core_CodeGen.c" } },
{ "pid": 1, "tid": 7, "ts": 39792324.21875, "dur": 3742.79999732971, "ph": "X", "name": "HashCompilerInvocation", "args": { "durationMS": 3.74279999732971, "detail": "UnityEngine.InputLegacyModule_CodeGen.c" } },
{ "pid": 1, "tid": 7, "ts": 39796386.71875, "dur": 959.59997177124, "ph": "X", "name": "HashCompilerInvocation", "args": { "durationMS": 0.95959997177124, "detail": "UnityEngine.ImageConversionModule.cpp" } },
{ "pid": 1, "tid": 7, "ts": 39797566.40625, "dur": 16364.4008636475, "ph": "X", "name": "HashCompilerInvocation", "args": { "durationMS": 16.3644008636475, "detail": "zutil.c" } },
{ "pid": 1, "tid": 7, "ts": 39814230.46875, "dur": 46344.0017700195, "ph": "X", "name": "HashCompilerInvocation", "args": { "durationMS": 46.3440017700195, "detail": "Il2CppCodeRegistration.cpp" } },
{ "pid": 1, "tid": 7, "ts": 39860769.53125, "dur": 441.799998283386, "ph": "X", "name": "HashCompilerInvocation", "args": { "durationMS": 0.441799998283386, "detail": "Lump_libil2cpp_utils.cpp" } },
{ "pid": 1, "tid": 7, "ts": 39861359.375, "dur": 369.599997997284, "ph": "X", "name": "HashCompilerInvocation", "args": { "durationMS": 0.369599997997284, "detail": "UnityEngine.PhysicsModule_CodeGen.c" } },
{ "pid": 1, "tid": 7, "ts": 39862238.28125, "dur": 363.299995660782, "ph": "X", "name": "HashCompilerInvocation", "args": { "durationMS": 0.363299995660782, "detail": "UnityEngine.ImageConversionModule_CodeGen.c" } },
{ "pid": 1, "tid": 7, "ts": 39862742.1875, "dur": 364.100009202957, "ph": "X", "name": "HashCompilerInvocation", "args": { "durationMS": 0.364100009202957, "detail": "Il2CppMetadataRegistration.c" } },
{ "pid": 1, "tid": 7, "ts": 39863242.1875, "dur": 15776.2002944946, "ph": "X", "name": "HashCompilerInvocation", "args": { "durationMS": 15.7762002944946, "detail": "netstandard.cpp" } },
{ "pid": 1, "tid": 7, "ts": 39879253.90625, "dur": 23042.0989990234, "ph": "X", "name": "HashCompilerInvocation", "args": { "durationMS": 23.0420989990234, "detail": "System.Diagnostics.StackTrace.cpp" } },
{ "pid": 1, "tid": 7, "ts": 39902617.1875, "dur": 1482.49995708466, "ph": "X", "name": "HashCompilerInvocation", "args": { "durationMS": 1.48249995708466, "detail": "Lump_libil2cpp_gc.cpp" } },
{ "pid": 1, "tid": 7, "ts": 39904261.71875, "dur": 405.499994754791, "ph": "X", "name": "HashCompilerInvocation", "args": { "durationMS": 0.405499994754791, "detail": "System.Diagnostics.StackTrace_CodeGen.c" } },
{ "pid": 1, "tid": 7, "ts": 39904804.6875, "dur": 590.499997138977, "ph": "X", "name": "HashCompilerInvocation", "args": { "durationMS": 0.590499997138977, "detail": "UnityEngine_CodeGen.c" } },
{ "pid": 1, "tid": 7, "ts": 39905550.78125, "dur": 435.900002717972, "ph": "X", "name": "HashCompilerInvocation", "args": { "durationMS": 0.435900002717972, "detail": "Lump_libil2cpp_codegen.cpp" } },
{ "pid": 1, "tid": 7, "ts": 39906832.03125, "dur": 559.700012207031, "ph": "X", "name": "HashCompilerInvocation", "args": { "durationMS": 0.559700012207031, "detail": "Lump_libil2cpp_debugger.cpp" } },
{ "pid": 1, "tid": 6, "ph": "M", "name": "thread_name", "args": { "name": "" } },
{ "pid": 1, "tid": 6, "ts": 35492632.8125, "dur": 29718.2006835938, "ph": "X", "name": "HashCompilerInvocation", "args": { "durationMS": 29.7182006835938, "detail": "Il2CppCompilerCalculateTypeValues.cpp" } },
{ "pid": 1, "tid": 6, "ts": 35522585.9375, "dur": 104926.10168457, "ph": "X", "name": "HashCompilerInvocation", "args": { "durationMS": 104.92610168457, "detail": "mscorlib_CodeGen.c" } },
{ "pid": 1, "tid": 6, "ts": 35627875, "dur": 374968.017578125, "ph": "X", "name": "HashCompilerInvocation", "args": { "durationMS": 374.968017578125, "detail": "mscorlib3.cpp" } },
{ "pid": 1, "tid": 6, "ts": 36003039.0625, "dur": 123641.395568848, "ph": "X", "name": "HashCompilerInvocation", "args": { "durationMS": 123.641395568848, "detail": "Il2CppGenericMethodPointerTable.cpp" } },
{ "pid": 1, "tid": 6, "ts": 36126933.59375, "dur": 411096.923828125, "ph": "X", "name": "HashCompilerInvocation", "args": { "durationMS": 411.096923828125, "detail": "GenericMethods.cpp" } },
{ "pid": 1, "tid": 6, "ts": 36538246.09375, "dur": 368816.589355469, "ph": "X", "name": "HashCompilerInvocation", "args": { "durationMS": 368.816589355469, "detail": "Generics.cpp" } },
{ "pid": 1, "tid": 6, "ts": 36907406.25, "dur": 393250.213623047, "ph": "X", "name": "HashCompilerInvocation", "args": { "durationMS": 393.250213623047, "detail": "GenericMethods3.cpp" } },
{ "pid": 1, "tid": 6, "ts": 37300964.84375, "dur": 8116.1003112793, "ph": "X", "name": "HashCompilerInvocation", "args": { "durationMS": 8.1161003112793, "detail": "mscorlib5.cpp" } },
{ "pid": 1, "tid": 6, "ts": 37309398.4375, "dur": 7174.79991912842, "ph": "X", "name": "HashCompilerInvocation", "args": { "durationMS": 7.17479991912842, "detail": "mscorlib8.cpp" } },
{ "pid": 1, "tid": 6, "ts": 37317136.71875, "dur": 402112.518310547, "ph": "X", "name": "HashCompilerInvocation", "args": { "durationMS": 402.112518310547, "detail": "mscorlib2.cpp" } },
{ "pid": 1, "tid": 6, "ts": 37719714.84375, "dur": 64670.0057983398, "ph": "X", "name": "HashCompilerInvocation", "args": { "durationMS": 64.6700057983398, "detail": "GenericMethods2.cpp" } },
{ "pid": 1, "tid": 6, "ts": 37784976.5625, "dur": 218124.588012695, "ph": "X", "name": "HashCompilerInvocation", "args": { "durationMS": 218.124588012695, "detail": "Generics8.cpp" } },
{ "pid": 1, "tid": 6, "ts": 38003363.28125, "dur": 59335.2012634277, "ph": "X", "name": "HashCompilerInvocation", "args": { "durationMS": 59.3352012634277, "detail": "Il2CppCompilerCalculateTypeValues1.cpp" } },
{ "pid": 1, "tid": 6, "ts": 38062992.1875, "dur": 294965.698242188, "ph": "X", "name": "HashCompilerInvocation", "args": { "durationMS": 294.965698242188, "detail": "System1.cpp" } },
{ "pid": 1, "tid": 6, "ts": 38358187.5, "dur": 188025.299072266, "ph": "X", "name": "HashCompilerInvocation", "args": { "durationMS": 188.025299072266, "detail": "Generics4.cpp" } },
{ "pid": 1, "tid": 6, "ts": 38546386.71875, "dur": 28968.7004089355, "ph": "X", "name": "HashCompilerInvocation", "args": { "durationMS": 28.9687004089355, "detail": "Il2CppGenericMethodTable.c" } },
{ "pid": 1, "tid": 6, "ts": 38575640.625, "dur": 122846.298217773, "ph": "X", "name": "HashCompilerInvocation", "args": { "durationMS": 122.846298217773, "detail": "Generics6.cpp" } },
{ "pid": 1, "tid": 6, "ts": 38698742.1875, "dur": 204104.81262207, "ph": "X", "name": "HashCompilerInvocation", "args": { "durationMS": 204.10481262207, "detail": "GenericMethods1.cpp" } },
{ "pid": 1, "tid": 6, "ts": 38903515.625, "dur": 165437.5, "ph": "X", "name": "HashCompilerInvocation", "args": { "durationMS": 165.4375, "detail": "mscorlib17.cpp" } },
{ "pid": 1, "tid": 6, "ts": 39069179.6875, "dur": 249509.399414063, "ph": "X", "name": "HashCompilerInvocation", "args": { "durationMS": 249.509399414063, "detail": "UnityEngine.UI_CodeGen.c" } },
{ "pid": 1, "tid": 6, "ts": 39318976.5625, "dur": 72014.7018432617, "ph": "X", "name": "HashCompilerInvocation", "args": { "durationMS": 72.0147018432617, "detail": "LeanTransition_CodeGen.c" } },
{ "pid": 1, "tid": 6, "ts": 39391207.03125, "dur": 126992.897033691, "ph": "X", "name": "HashCompilerInvocation", "args": { "durationMS": 126.992897033691, "detail": "Mono.Security.cpp" } },
{ "pid": 1, "tid": 6, "ts": 39518367.1875, "dur": 83765.6021118164, "ph": "X", "name": "HashCompilerInvocation", "args": { "durationMS": 83.7656021118164, "detail": "System.Configuration.cpp" } },
{ "pid": 1, "tid": 6, "ts": 39602382.8125, "dur": 46880.500793457, "ph": "X", "name": "HashCompilerInvocation", "args": { "durationMS": 46.880500793457, "detail": "il2cpp-api.cpp" } },
{ "pid": 1, "tid": 6, "ts": 39649496.09375, "dur": 7783.29992294312, "ph": "X", "name": "HashCompilerInvocation", "args": { "durationMS": 7.78329992294312, "detail": "UnityEngine.UnityWebRequestModule_CodeGen.c" } },
{ "pid": 1, "tid": 6, "ts": 39657488.28125, "dur": 48309.5016479492, "ph": "X", "name": "HashCompilerInvocation", "args": { "durationMS": 48.3095016479492, "detail": "UnityEngine.UIModule_CodeGen.c" } },
{ "pid": 1, "tid": 6, "ts": 39706078.125, "dur": 20508.3999633789, "ph": "X", "name": "HashCompilerInvocation", "args": { "durationMS": 20.5083999633789, "detail": "UnityEngine.AnimationModule_CodeGen.c" } },
{ "pid": 1, "tid": 6, "ts": 39726800.78125, "dur": 32580.0018310547, "ph": "X", "name": "HashCompilerInvocation", "args": { "durationMS": 32.5800018310547, "detail": "gzlib.c" } },
{ "pid": 1, "tid": 6, "ts": 39759542.96875, "dur": 31364.5000457764, "ph": "X", "name": "HashCompilerInvocation", "args": { "durationMS": 31.3645000457764, "detail": "UnityEngine.AudioModule_CodeGen.c" } },
{ "pid": 1, "tid": 6, "ts": 39791140.625, "dur": 17133.2988739014, "ph": "X", "name": "HashCompilerInvocation", "args": { "durationMS": 17.1332988739014, "detail": "inffast.c" } },
{ "pid": 1, "tid": 6, "ts": 39808468.75, "dur": 39466.2017822266, "ph": "X", "name": "HashCompilerInvocation", "args": { "durationMS": 39.4662017822266, "detail": "adler32.c" } },
{ "pid": 1, "tid": 6, "ts": 39848156.25, "dur": 738.600015640259, "ph": "X", "name": "HashCompilerInvocation", "args": { "durationMS": 0.738600015640259, "detail": "UnityEngine.UnityWebRequestWWWModule_CodeGen.c" } },
{ "pid": 1, "tid": 6, "ts": 39849101.5625, "dur": 1142.19999313354, "ph": "X", "name": "HashCompilerInvocation", "args": { "durationMS": 1.14219999313354, "detail": "Lump_libil2cpp_metadata.cpp" } },
{ "pid": 1, "tid": 6, "ts": 39850441.40625, "dur": 48013.599395752, "ph": "X", "name": "HashCompilerInvocation", "args": { "durationMS": 48.013599395752, "detail": "UnityAdsStubs.cpp" } },
{ "pid": 1, "tid": 6, "ts": 39898695.3125, "dur": 11060.2998733521, "ph": "X", "name": "HashCompilerInvocation", "args": { "durationMS": 11.0602998733521, "detail": "il2cpp-benchmark-support.cpp" } },
{ "pid": 1, "tid": 5, "ph": "M", "name": "thread_name", "args": { "name": "" } },
{ "pid": 1, "tid": 5, "ts": 35492664.0625, "dur": 330739.501953125, "ph": "X", "name": "HashCompilerInvocation", "args": { "durationMS": 330.739501953125, "detail": "Il2CppAttributes.cpp" } },
{ "pid": 1, "tid": 5, "ts": 35823734.375, "dur": 106068.695068359, "ph": "X", "name": "HashCompilerInvocation", "args": { "durationMS": 106.068695068359, "detail": "UnityEngine.UI.cpp" } },
{ "pid": 1, "tid": 5, "ts": 35930078.125, "dur": 474342.712402344, "ph": "X", "name": "HashCompilerInvocation", "args": { "durationMS": 474.342712402344, "detail": "mscorlib11.cpp" } },
{ "pid": 1, "tid": 5, "ts": 36404652.34375, "dur": 444628.692626953, "ph": "X", "name": "HashCompilerInvocation", "args": { "durationMS": 444.628692626953, "detail": "mscorlib1.cpp" } },
{ "pid": 1, "tid": 5, "ts": 36849636.71875, "dur": 432756.134033203, "ph": "X", "name": "HashCompilerInvocation", "args": { "durationMS": 432.756134033203, "detail": "UnityEngine.UI1.cpp" } },
{ "pid": 1, "tid": 5, "ts": 37282855.46875, "dur": 485891.11328125, "ph": "X", "name": "HashCompilerInvocation", "args": { "durationMS": 485.89111328125, "detail": "Generics11.cpp" } },
{ "pid": 1, "tid": 5, "ts": 37769000, "dur": 208615.295410156, "ph": "X", "name": "HashCompilerInvocation", "args": { "durationMS": 208.615295410156, "detail": "LeanTransition.cpp" } },
{ "pid": 1, "tid": 5, "ts": 37977832.03125, "dur": 293111.297607422, "ph": "X", "name": "HashCompilerInvocation", "args": { "durationMS": 293.111297607422, "detail": "Il2CppGenericMethodDefinitions.c" } },
{ "pid": 1, "tid": 5, "ts": 38271148.4375, "dur": 120472.602844238, "ph": "X", "name": "HashCompilerInvocation", "args": { "durationMS": 120.472602844238, "detail": "Generics1.cpp" } },
{ "pid": 1, "tid": 5, "ts": 38391835.9375, "dur": 171401.000976563, "ph": "X", "name": "HashCompilerInvocation", "args": { "durationMS": 171.401000976563, "detail": "UnityEngine.CoreModule1.cpp" } },
{ "pid": 1, "tid": 5, "ts": 38563484.375, "dur": 168957.397460938, "ph": "X", "name": "HashCompilerInvocation", "args": { "durationMS": 168.957397460938, "detail": "Generics12.cpp" } },
{ "pid": 1, "tid": 5, "ts": 38732695.3125, "dur": 185197.58605957, "ph": "X", "name": "HashCompilerInvocation", "args": { "durationMS": 185.19758605957, "detail": "Il2CppGenericClassTable.c" } },
{ "pid": 1, "tid": 5, "ts": 38918117.1875, "dur": 146867.401123047, "ph": "X", "name": "HashCompilerInvocation", "args": { "durationMS": 146.867401123047, "detail": "UnityEngine.IMGUIModule.cpp" } },
{ "pid": 1, "tid": 5, "ts": 39065324.21875, "dur": 117546.806335449, "ph": "X", "name": "HashCompilerInvocation", "args": { "durationMS": 117.546806335449, "detail": "UnityEngine.UnityWebRequestModule.cpp" } },
{ "pid": 1, "tid": 5, "ts": 39183097.65625, "dur": 79852.6992797852, "ph": "X", "name": "HashCompilerInvocation", "args": { "durationMS": 79.8526992797852, "detail": "UnityEngine.AnimationModule.cpp" } },
{ "pid": 1, "tid": 5, "ts": 39263156.25, "dur": 112830.192565918, "ph": "X", "name": "HashCompilerInvocation", "args": { "durationMS": 112.830192565918, "detail": "UnityEngine.TextRenderingModule.cpp" } },
{ "pid": 1, "tid": 5, "ts": 39376203.125, "dur": 78303.3981323242, "ph": "X", "name": "HashCompilerInvocation", "args": { "durationMS": 78.3033981323242, "detail": "UnityEngine.SharedInternalsModule.cpp" } },
{ "pid": 1, "tid": 5, "ts": 39454746.09375, "dur": 34519.2985534668, "ph": "X", "name": "HashCompilerInvocation", "args": { "durationMS": 34.5192985534668, "detail": "LeanCommon.cpp" } },
{ "pid": 1, "tid": 5, "ts": 39489480.46875, "dur": 44212.100982666, "ph": "X", "name": "HashCompilerInvocation", "args": { "durationMS": 44.212100982666, "detail": "deflate.c" } },
{ "pid": 1, "tid": 5, "ts": 39534250, "dur": 26303.9016723633, "ph": "X", "name": "HashCompilerInvocation", "args": { "durationMS": 26.3039016723633, "detail": "UnityEngine.IMGUIModule_CodeGen.c" } },
{ "pid": 1, "tid": 5, "ts": 39560753.90625, "dur": 60505.9013366699, "ph": "X", "name": "HashCompilerInvocation", "args": { "durationMS": 60.5059013366699, "detail": "UnityEngine.UnityWebRequestWWWModule.cpp" } },
{ "pid": 1, "tid": 5, "ts": 39621562.5, "dur": 35802.2003173828, "ph": "X", "name": "HashCompilerInvocation", "args": { "durationMS": 35.8022003173828, "detail": "UnityEngine.UI3.cpp" } },
{ "pid": 1, "tid": 5, "ts": 39657519.53125, "dur": 35566.2002563477, "ph": "X", "name": "HashCompilerInvocation", "args": { "durationMS": 35.5662002563477, "detail": "infback.c" } },
{ "pid": 1, "tid": 5, "ts": 39693296.875, "dur": 55017.6010131836, "ph": "X", "name": "HashCompilerInvocation", "args": { "durationMS": 55.0176010131836, "detail": "gzread.c" } },
{ "pid": 1, "tid": 5, "ts": 39748539.0625, "dur": 3444.00000572205, "ph": "X", "name": "HashCompilerInvocation", "args": { "durationMS": 3.44400000572205, "detail": "UnityClassRegistration.cpp" } },
{ "pid": 1, "tid": 5, "ts": 39752218.75, "dur": 979.600012302399, "ph": "X", "name": "HashCompilerInvocation", "args": { "durationMS": 0.979600012302399, "detail": "UnityEngine.SharedInternalsModule_CodeGen.c" } },
{ "pid": 1, "tid": 5, "ts": 39753929.6875, "dur": 925.300002098083, "ph": "X", "name": "HashCompilerInvocation", "args": { "durationMS": 0.925300002098083, "detail": "UnityEngine.Physics2DModule_CodeGen.c" } },
{ "pid": 1, "tid": 5, "ts": 39755062.5, "dur": 43379.0016174316, "ph": "X", "name": "HashCompilerInvocation", "args": { "durationMS": 43.3790016174316, "detail": "crc32.c" } },
{ "pid": 1, "tid": 5, "ts": 39798675.78125, "dur": 3148.69999885559, "ph": "X", "name": "HashCompilerInvocation", "args": { "durationMS": 3.14869999885559, "detail": "LeanCommon_CodeGen.c" } },
{ "pid": 1, "tid": 5, "ts": 39802066.40625, "dur": 3742.5000667572, "ph": "X", "name": "HashCompilerInvocation", "args": { "durationMS": 3.7425000667572, "detail": "System.Configuration_CodeGen.c" } },
{ "pid": 1, "tid": 5, "ts": 39806050.78125, "dur": 17613.1000518799, "ph": "X", "name": "HashCompilerInvocation", "args": { "durationMS": 17.6131000518799, "detail": "UnityEngine.UnityAnalyticsModule_CodeGen.c" } },
{ "pid": 1, "tid": 5, "ts": 39823921.875, "dur": 474.900007247925, "ph": "X", "name": "HashCompilerInvocation", "args": { "durationMS": 0.474900007247925, "detail": "Lump_libil2cpp_vm.cpp" } },
{ "pid": 1, "tid": 5, "ts": 39824542.96875, "dur": 3492.5000667572, "ph": "X", "name": "HashCompilerInvocation", "args": { "durationMS": 3.4925000667572, "detail": "gc.c" } },
{ "pid": 1, "tid": 5, "ts": 39828214.84375, "dur": 382.299989461899, "ph": "X", "name": "HashCompilerInvocation", "args": { "durationMS": 0.382299989461899, "detail": "Il2CppReversePInvokeWrapperTable.cpp" } },
{ "pid": 1, "tid": 5, "ts": 39828750, "dur": 64541.2979125977, "ph": "X", "name": "HashCompilerInvocation", "args": { "durationMS": 64.5412979125977, "detail": "uncompr.c" } },
{ "pid": 1, "tid": 5, "ts": 39893531.25, "dur": 525.200009346008, "ph": "X", "name": "HashCompilerInvocation", "args": { "durationMS": 0.525200009346008, "detail": "UnityEngine.cpp" } },
{ "pid": 1, "tid": 5, "ts": 39894246.09375, "dur": 414.200007915497, "ph": "X", "name": "HashCompilerInvocation", "args": { "durationMS": 0.414200007915497, "detail": "Lump_libil2cpp_mono.cpp" } },
{ "pid": 1, "tid": 5, "ts": 39894812.5, "dur": 416.900008916855, "ph": "X", "name": "HashCompilerInvocation", "args": { "durationMS": 0.416900008916855, "detail": "System.Xml_CodeGen.c" } },
{ "pid": 1, "tid": 5, "ts": 39895375, "dur": 11560.6002807617, "ph": "X", "name": "HashCompilerInvocation", "args": { "durationMS": 11.5606002807617, "detail": "gzclose.c" } },
{ "pid": 1, "tid": 5, "ts": 39907105.46875, "dur": 6029.09994125366, "ph": "X", "name": "HashCompilerInvocation", "args": { "durationMS": 6.02909994125366, "detail": "il2cpp-runtime-stats.cpp" } },
{ "pid": 1, "tid": 4, "ph": "M", "name": "thread_name", "args": { "name": "" } },
{ "pid": 1, "tid": 4, "ts": 35492707.03125, "dur": 34159.0995788574, "ph": "X", "name": "HashCompilerInvocation", "args": { "durationMS": 34.1590995788574, "detail": "Il2CppTypeDefinitions.c" } },
{ "pid": 1, "tid": 4, "ts": 35527023.4375, "dur": 911939.575195313, "ph": "X", "name": "HashCompilerInvocation", "args": { "durationMS": 911.939575195313, "detail": "mscorlib4.cpp" } },
{ "pid": 1, "tid": 4, "ts": 36439160.15625, "dur": 272813.995361328, "ph": "X", "name": "HashCompilerInvocation", "args": { "durationMS": 272.813995361328, "detail": "mscorlib16.cpp" } },
{ "pid": 1, "tid": 4, "ts": 36712179.6875, "dur": 375640.197753906, "ph": "X", "name": "HashCompilerInvocation", "args": { "durationMS": 375.640197753906, "detail": "mscorlib10.cpp" } },
{ "pid": 1, "tid": 4, "ts": 37088019.53125, "dur": 283903.3203125, "ph": "X", "name": "HashCompilerInvocation", "args": { "durationMS": 283.9033203125, "detail": "mscorlib15.cpp" } },
{ "pid": 1, "tid": 4, "ts": 37372125, "dur": 476160.522460938, "ph": "X", "name": "HashCompilerInvocation", "args": { "durationMS": 476.160522460938, "detail": "mscorlib13.cpp" } },
{ "pid": 1, "tid": 4, "ts": 37848738.28125, "dur": 498167.816162109, "ph": "X", "name": "HashCompilerInvocation", "args": { "durationMS": 498.167816162109, "detail": "mscorlib14.cpp" } },
{ "pid": 1, "tid": 4, "ts": 38347160.15625, "dur": 366476.287841797, "ph": "X", "name": "HashCompilerInvocation", "args": { "durationMS": 366.476287841797, "detail": "Generics2.cpp" } },
{ "pid": 1, "tid": 4, "ts": 38713875, "dur": 195447.998046875, "ph": "X", "name": "HashCompilerInvocation", "args": { "durationMS": 195.447998046875, "detail": "Assembly-CSharp.cpp" } },
{ "pid": 1, "tid": 4, "ts": 38909808.59375, "dur": 176250.80871582, "ph": "X", "name": "HashCompilerInvocation", "args": { "durationMS": 176.25080871582, "detail": "Il2CppGenericInstDefinitions.c" } },
{ "pid": 1, "tid": 4, "ts": 39086285.15625, "dur": 55191.2002563477, "ph": "X", "name": "HashCompilerInvocation", "args": { "durationMS": 55.1912002563477, "detail": "char-conversions.cpp" } },
{ "pid": 1, "tid": 4, "ts": 39141683.59375, "dur": 26602.3998260498, "ph": "X", "name": "HashCompilerInvocation", "args": { "durationMS": 26.6023998260498, "detail": "UnresolvedVirtualCallStubs.cpp" } },
{ "pid": 1, "tid": 4, "ts": 39168734.375, "dur": 115048.896789551, "ph": "X", "name": "HashCompilerInvocation", "args": { "durationMS": 115.048896789551, "detail": "System2.cpp" } },
{ "pid": 1, "tid": 4, "ts": 39284113.28125, "dur": 13198.8000869751, "ph": "X", "name": "HashCompilerInvocation", "args": { "durationMS": 13.1988000869751, "detail": "System_CodeGen.c" } },
{ "pid": 1, "tid": 4, "ts": 39297511.71875, "dur": 159757.095336914, "ph": "X", "name": "HashCompilerInvocation", "args": { "durationMS": 159.757095336914, "detail": "UnityEngine.Physics2DModule.cpp" } },
{ "pid": 1, "tid": 4, "ts": 39457484.375, "dur": 24068.7007904053, "ph": "X", "name": "HashCompilerInvocation", "args": { "durationMS": 24.0687007904053, "detail": "UnityICallRegistration.cpp" } },
{ "pid": 1, "tid": 4, "ts": 39481824.21875, "dur": 36275.5012512207, "ph": "X", "name": "HashCompilerInvocation", "args": { "durationMS": 36.2755012512207, "detail": "LeanGUI_CodeGen.c" } },
{ "pid": 1, "tid": 4, "ts": 39518308.59375, "dur": 67982.9025268555, "ph": "X", "name": "HashCompilerInvocation", "args": { "durationMS": 67.9829025268555, "detail": "UnityEngine.UnityAnalyticsModule.cpp" } },
{ "pid": 1, "tid": 4, "ts": 39586488.28125, "dur": 57725.1014709473, "ph": "X", "name": "HashCompilerInvocation", "args": { "durationMS": 57.7251014709473, "detail": "trees.c" } },
{ "pid": 1, "tid": 4, "ts": 39644445.3125, "dur": 44506.7024230957, "ph": "X", "name": "HashCompilerInvocation", "args": { "durationMS": 44.5067024230957, "detail": "xamarin_getifaddrs.c" } },
{ "pid": 1, "tid": 4, "ts": 39689164.0625, "dur": 84112.6022338867, "ph": "X", "name": "HashCompilerInvocation", "args": { "durationMS": 84.1126022338867, "detail": "System.Core.cpp" } },
{ "pid": 1, "tid": 4, "ts": 39773500, "dur": 29707.0999145508, "ph": "X", "name": "HashCompilerInvocation", "args": { "durationMS": 29.7070999145508, "detail": "inftrees.c" } },
{ "pid": 1, "tid": 4, "ts": 39803402.34375, "dur": 20406.4998626709, "ph": "X", "name": "HashCompilerInvocation", "args": { "durationMS": 20.4064998626709, "detail": "System.Xml.cpp" } },
{ "pid": 1, "tid": 4, "ts": 39824031.25, "dur": 17314.3997192383, "ph": "X", "name": "HashCompilerInvocation", "args": { "durationMS": 17.3143997192383, "detail": "Mono.Security_CodeGen.c" } },
{ "pid": 1, "tid": 4, "ts": 39841566.40625, "dur": 49083.3969116211, "ph": "X", "name": "HashCompilerInvocation", "args": { "durationMS": 49.0833969116211, "detail": "compress.c" } },
{ "pid": 1, "tid": 4, "ts": 39890968.75, "dur": 11317.099571228, "ph": "X", "name": "HashCompilerInvocation", "args": { "durationMS": 11.317099571228, "detail": "System.Globalization.Extensions.cpp" } },
{ "pid": 1, "tid": 4, "ts": 39902515.625, "dur": 1501.09994411469, "ph": "X", "name": "HashCompilerInvocation", "args": { "durationMS": 1.50109994411469, "detail": "Lump_libil2cpp_vm-utils.cpp" } },
{ "pid": 1, "tid": 4, "ts": 39904214.84375, "dur": 415.199995040894, "ph": "X", "name": "HashCompilerInvocation", "args": { "durationMS": 0.415199995040894, "detail": "System.Globalization.Extensions_CodeGen.c" } },
{ "pid": 1, "tid": 4, "ts": 39904777.34375, "dur": 396.899998188019, "ph": "X", "name": "HashCompilerInvocation", "args": { "durationMS": 0.396899998188019, "detail": "netstandard_CodeGen.c" } },
{ "pid": 1, "tid": 4, "ts": 39905316.40625, "dur": 375, "ph": "X", "name": "HashCompilerInvocation", "args": { "durationMS": 0.375, "detail": "Lump_libil2cpp_mono-runtime.cpp" } },
{ "pid": 1, "tid": 4, "ts": 39905832.03125, "dur": 1172.89996147156, "ph": "X", "name": "HashCompilerInvocation", "args": { "durationMS": 1.17289996147156, "detail": "Il2CppGenericComDefinitions.cpp" } },
{ "pid": 1, "tid": 8, "ph": "M", "name": "thread_name", "args": { "name": "" } },
{ "pid": 1, "tid": 8, "ts": 39918179.6875, "dur": 13258354.4921875, "ph": "X", "name": "Compile", "args": { "durationMS": 13258.3544921875, "detail": "Il2CppMetadataUsage.c" } },
{ "pid": 1, "tid": 11, "ph": "M", "name": "thread_name", "args": { "name": "" } },
{ "pid": 1, "tid": 11, "ts": 39918183.59375, "dur": 13115727.5390625, "ph": "X", "name": "Compile", "args": { "durationMS": 13115.7275390625, "detail": "Il2CppCompilerCalculateTypeValuesTable.cpp" } },
{ "pid": 1, "tid": 11, "ts": 53034699.21875, "dur": 2182327.39257813, "ph": "X", "name": "Compile", "args": { "durationMS": 2182.32739257813, "detail": "Assembly-CSharp_CodeGen.c" } },
{ "pid": 1, "tid": 9, "ph": "M", "name": "thread_name", "args": { "name": "" } },
{ "pid": 1, "tid": 9, "ts": 39918277.34375, "dur": 13125659.1796875, "ph": "X", "name": "Compile", "args": { "durationMS": 13125.6591796875, "detail": "Il2CppCompilerCalculateTypeValues1.cpp" } },
{ "pid": 1, "tid": 9, "ts": 53043945.3125, "dur": 1900761.47460938, "ph": "X", "name": "Compile", "args": { "durationMS": 1900.76147460938, "detail": "Il2CppMetadataRegistration.c" } },
{ "pid": 1, "tid": 10, "ph": "M", "name": "thread_name", "args": { "name": "" } },
{ "pid": 1, "tid": 10, "ts": 39918449.21875, "dur": 15424133.7890625, "ph": "X", "name": "Compile", "args": { "durationMS": 15424.1337890625, "detail": "Assembly-CSharp.cpp" } }
],
"meta_datetime": "10/18/2020 11:54:54",
"meta_command_line": "\"D:\\Program Files\\Unity\\Install\\2019.2.13f1\\Editor\\Data\\il2cpp/build/il2cpp.exe\" --convert-to-cpp --dotnetprofile=\"unityaot\" --compile-cpp --libil2cpp-static --platform=\"WebGL\" --architecture=\"EmscriptenJavaScript\" --configuration=\"Release\" --outputpath=\"D:\\Documents\\Faks\\Diplomski Rad Prototiip\\WaterSystemPrototype\\Water System Prototype\\Assets /../Temp/StagingArea/Data\\Native\\build.bc\" --cachedirectory=\"D:\\Documents\\Faks\\Diplomski Rad Prototiip\\WaterSystemPrototype\\Water System Prototype\\Assets\\..\\Library/il2cpp_cache\" --compiler-flags=\"-Oz -DIL2CPP_EXCEPTION_DISABLED=1 \" --emit-method-map --additional-libraries=\"D:/Program Files/Unity/Install/2019.2.13f1/Editor/Data/PlaybackEngines/WebGLSupport\\BuildTools\\lib\\modules\\WebGLSupport_AccessibilityModule_Dynamic.bc\" --additional-libraries=\"D:/Program Files/Unity/Install/2019.2.13f1/Editor/Data/PlaybackEngines/WebGLSupport\\BuildTools\\lib\\modules\\WebGLSupport_AIModule_Dynamic.bc\" --additional-libraries=\"D:/Program Files/Unity/Install/2019.2.13f1/Editor/Data/PlaybackEngines/WebGLSupport\\BuildTools\\lib\\modules\\WebGLSupport_AndroidJNIModule_Dynamic.bc\" --additional-libraries=\"D:/Program Files/Unity/Install/2019.2.13f1/Editor/Data/PlaybackEngines/WebGLSupport\\BuildTools\\lib\\modules\\WebGLSupport_AnimationModule_Dynamic.bc\" --additional-libraries=\"D:/Program Files/Unity/Install/2019.2.13f1/Editor/Data/PlaybackEngines/WebGLSupport\\BuildTools\\lib\\modules\\WebGLSupport_ARModule_Dynamic.bc\" --additional-libraries=\"D:/Program Files/Unity/Install/2019.2.13f1/Editor/Data/PlaybackEngines/WebGLSupport\\BuildTools\\lib\\modules\\WebGLSupport_AssetBundleModule_Dynamic.bc\" --additional-libraries=\"D:/Program Files/Unity/Install/2019.2.13f1/Editor/Data/PlaybackEngines/WebGLSupport\\BuildTools\\lib\\modules\\WebGLSupport_AudioModule_Dynamic.bc\" --additional-libraries=\"D:/Program Files/Unity/Install/2019.2.13f1/Editor/Data/PlaybackEngines/WebGLSupport\\BuildTools\\lib\\modules\\WebGLSupport_ClothModule_Dynamic.bc\" --additional-libraries=\"D:/Program Files/Unity/Install/2019.2.13f1/Editor/Data/PlaybackEngines/WebGLSupport\\BuildTools\\lib\\modules\\WebGLSupport_CoreModule_Dynamic.bc\" --additional-libraries=\"D:/Program Files/Unity/Install/2019.2.13f1/Editor/Data/PlaybackEngines/WebGLSupport\\BuildTools\\lib\\modules\\WebGLSupport_CrashReportingModule_Dynamic.bc\" --additional-libraries=\"D:/Program Files/Unity/Install/2019.2.13f1/Editor/Data/PlaybackEngines/WebGLSupport\\BuildTools\\lib\\modules\\WebGLSupport_DirectorModule_Dynamic.bc\" --additional-libraries=\"D:/Program Files/Unity/Install/2019.2.13f1/Editor/Data/PlaybackEngines/WebGLSupport\\BuildTools\\lib\\modules\\WebGLSupport_DSPGraphModule_Dynamic.bc\" --additional-libraries=\"D:/Program Files/Unity/Install/2019.2.13f1/Editor/Data/PlaybackEngines/WebGLSupport\\BuildTools\\lib\\modules\\WebGLSupport_FileSystemHttpModule_Dynamic.bc\" --additional-libraries=\"D:/Program Files/Unity/Install/2019.2.13f1/Editor/Data/PlaybackEngines/WebGLSupport\\BuildTools\\lib\\modules\\WebGLSupport_GameCenterModule_Dynamic.bc\" --additional-libraries=\"D:/Program Files/Unity/Install/2019.2.13f1/Editor/Data/PlaybackEngines/WebGLSupport\\BuildTools\\lib\\modules\\WebGLSupport_GridModule_Dynamic.bc\" --additional-libraries=\"D:/Program Files/Unity/Install/2019.2.13f1/Editor/Data/PlaybackEngines/WebGLSupport\\BuildTools\\lib\\modules\\WebGLSupport_HotReloadModule_Dynamic.bc\" --additional-libraries=\"D:/Program Files/Unity/Install/2019.2.13f1/Editor/Data/PlaybackEngines/WebGLSupport\\BuildTools\\lib\\modules\\WebGLSupport_ImageConversionModule_Dynamic.bc\" --additional-libraries=\"D:/Program Files/Unity/Install/2019.2.13f1/Editor/Data/PlaybackEngines/WebGLSupport\\BuildTools\\lib\\modules\\WebGLSupport_IMGUIModule_Dynamic.bc\" --additional-libraries=\"D:/Program Files/Unity/Install/2019.2.13f1/Editor/Data/PlaybackEngines/WebGLSupport\\BuildTools\\lib\\modules\\WebGLSupport_InputLegacyModule_Dynamic.bc\" --additional-libraries=\"D:/Program Files/Unity/Install/2019.2.13f1/Editor/Data/PlaybackEngines/WebGLSupport\\BuildTools\\lib\\modules\\WebGLSupport_InputModule_Dynamic.bc\" --additional-libraries=\"D:/Program Files/Unity/Install/2019.2.13f1/Editor/Data/PlaybackEngines/WebGLSupport\\BuildTools\\lib\\modules\\WebGLSupport_JSONSerializeModule_Dynamic.bc\" --additional-libraries=\"D:/Program Files/Unity/Install/2019.2.13f1/Editor/Data/PlaybackEngines/WebGLSupport\\BuildTools\\lib\\modules\\WebGLSupport_LocalizationModule_Dynamic.bc\" --additional-libraries=\"D:/Program Files/Unity/Install/2019.2.13f1/Editor/Data/PlaybackEngines/WebGLSupport\\BuildTools\\lib\\modules\\WebGLSupport_ParticleSystemModule_Dynamic.bc\" --additional-libraries=\"D:/Program Files/Unity/Install/2019.2.13f1/Editor/Data/PlaybackEngines/WebGLSupport\\BuildTools\\lib\\modules\\WebGLSupport_PerformanceReportingModule_Dynamic.bc\" --additional-libraries=\"D:/Program Files/Unity/Install/2019.2.13f1/Editor/Data/PlaybackEngines/WebGLSupport\\BuildTools\\lib\\modules\\WebGLSupport_Physics2DModule_Dynamic.bc\" --additional-libraries=\"D:/Program Files/Unity/Install/2019.2.13f1/Editor/Data/PlaybackEngines/WebGLSupport\\BuildTools\\lib\\modules\\WebGLSupport_PhysicsModule_Dynamic.bc\" --additional-libraries=\"D:/Program Files/Unity/Install/2019.2.13f1/Editor/Data/PlaybackEngines/WebGLSupport\\BuildTools\\lib\\modules\\WebGLSupport_ProfilerModule_Dynamic.bc\" --additional-libraries=\"D:/Program Files/Unity/Install/2019.2.13f1/Editor/Data/PlaybackEngines/WebGLSupport\\BuildTools\\lib\\modules\\WebGLSupport_ScreenCaptureModule_Dynamic.bc\" --additional-libraries=\"D:/Program Files/Unity/Install/2019.2.13f1/Editor/Data/PlaybackEngines/WebGLSupport\\BuildTools\\lib\\modules\\WebGLSupport_SharedInternalsModule_Dynamic.bc\" --additional-libraries=\"D:/Program Files/Unity/Install/2019.2.13f1/Editor/Data/PlaybackEngines/WebGLSupport\\BuildTools\\lib\\modules\\WebGLSupport_SpriteMaskModule_Dynamic.bc\" --additional-libraries=\"D:/Program Files/Unity/Install/2019.2.13f1/Editor/Data/PlaybackEngines/WebGLSupport\\BuildTools\\lib\\modules\\WebGLSupport_SpriteShapeModule_Dynamic.bc\" --additional-libraries=\"D:/Program Files/Unity/Install/2019.2.13f1/Editor/Data/PlaybackEngines/WebGLSupport\\BuildTools\\lib\\modules\\WebGLSupport_StreamingModule_Dynamic.bc\" --additional-libraries=\"D:/Program Files/Unity/Install/2019.2.13f1/Editor/Data/PlaybackEngines/WebGLSupport\\BuildTools\\lib\\modules\\WebGLSupport_SubstanceModule_Dynamic.bc\" --additional-libraries=\"D:/Program Files/Unity/Install/2019.2.13f1/Editor/Data/PlaybackEngines/WebGLSupport\\BuildTools\\lib\\modules\\WebGLSupport_TerrainModule_Dynamic.bc\" --additional-libraries=\"D:/Program Files/Unity/Install/2019.2.13f1/Editor/Data/PlaybackEngines/WebGLSupport\\BuildTools\\lib\\modules\\WebGLSupport_TerrainPhysicsModule_Dynamic.bc\" --additional-libraries=\"D:/Program Files/Unity/Install/2019.2.13f1/Editor/Data/PlaybackEngines/WebGLSupport\\BuildTools\\lib\\modules\\WebGLSupport_TextCoreModule_Dynamic.bc\" --additional-libraries=\"D:/Program Files/Unity/Install/2019.2.13f1/Editor/Data/PlaybackEngines/WebGLSupport\\BuildTools\\lib\\modules\\WebGLSupport_TextRenderingModule_Dynamic.bc\" --additional-libraries=\"D:/Program Files/Unity/Install/2019.2.13f1/Editor/Data/PlaybackEngines/WebGLSupport\\BuildTools\\lib\\modules\\WebGLSupport_TilemapModule_Dynamic.bc\" --additional-libraries=\"D:/Program Files/Unity/Install/2019.2.13f1/Editor/Data/PlaybackEngines/WebGLSupport\\BuildTools\\lib\\modules\\WebGLSupport_TLSModule_Dynamic.bc\" --additional-libraries=\"D:/Program Files/Unity/Install/2019.2.13f1/Editor/Data/PlaybackEngines/WebGLSupport\\BuildTools\\lib\\modules\\WebGLSupport_UIElementsModule_Dynamic.bc\" --additional-libraries=\"D:/Program Files/Unity/Install/2019.2.13f1/Editor/Data/PlaybackEngines/WebGLSupport\\BuildTools\\lib\\modules\\WebGLSupport_UIModule_Dynamic.bc\" --additional-libraries=\"D:/Program Files/Unity/Install/2019.2.13f1/Editor/Data/PlaybackEngines/WebGLSupport\\BuildTools\\lib\\modules\\WebGLSupport_UmbraModule_Dynamic.bc\" --additional-libraries=\"D:/Program Files/Unity/Install/2019.2.13f1/Editor/Data/PlaybackEngines/WebGLSupport\\BuildTools\\lib\\modules\\WebGLSupport_UNETModule_Dynamic.bc\" --additional-libraries=\"D:/Program Files/Unity/Install/2019.2.13f1/Editor/Data/PlaybackEngines/WebGLSupport\\BuildTools\\lib\\modules\\WebGLSupport_UnityAnalyticsModule_Dynamic.bc\" --additional-libraries=\"D:/Program Files/Unity/Install/2019.2.13f1/Editor/Data/PlaybackEngines/WebGLSupport\\BuildTools\\lib\\modules\\WebGLSupport_UnityConnectModule_Dynamic.bc\" --additional-libraries=\"D:/Program Files/Unity/Install/2019.2.13f1/Editor/Data/PlaybackEngines/WebGLSupport\\BuildTools\\lib\\modules\\WebGLSupport_UnityTestProtocolModule_Dynamic.bc\" --additional-libraries=\"D:/Program Files/Unity/Install/2019.2.13f1/Editor/Data/PlaybackEngines/WebGLSupport\\BuildTools\\lib\\modules\\WebGLSupport_UnityWebRequestAssetBundleModule_Dynamic.bc\" --additional-libraries=\"D:/Program Files/Unity/Install/2019.2.13f1/Editor/Data/PlaybackEngines/WebGLSupport\\BuildTools\\lib\\modules\\WebGLSupport_UnityWebRequestAudioModule_Dynamic.bc\" --additional-libraries=\"D:/Program Files/Unity/Install/2019.2.13f1/Editor/Data/PlaybackEngines/WebGLSupport\\BuildTools\\lib\\modules\\WebGLSupport_UnityWebRequestModule_Dynamic.bc\" --additional-libraries=\"D:/Program Files/Unity/Install/2019.2.13f1/Editor/Data/PlaybackEngines/WebGLSupport\\BuildTools\\lib\\modules\\WebGLSupport_UnityWebRequestTextureModule_Dynamic.bc\" --additional-libraries=\"D:/Program Files/Unity/Install/2019.2.13f1/Editor/Data/PlaybackEngines/WebGLSupport\\BuildTools\\lib\\modules\\WebGLSupport_UnityWebRequestWWWModule_Dynamic.bc\" --additional-libraries=\"D:/Program Files/Unity/Install/2019.2.13f1/Editor/Data/PlaybackEngines/WebGLSupport\\BuildTools\\lib\\modules\\WebGLSupport_VehiclesModule_Dynamic.bc\" --additional-libraries=\"D:/Program Files/Unity/Install/2019.2.13f1/Editor/Data/PlaybackEngines/WebGLSupport\\BuildTools\\lib\\modules\\WebGLSupport_VFXModule_Dynamic.bc\" --additional-libraries=\"D:/Program Files/Unity/Install/2019.2.13f1/Editor/Data/PlaybackEngines/WebGLSupport\\BuildTools\\lib\\modules\\WebGLSupport_VideoModule_Dynamic.bc\" --additional-libraries=\"D:/Program Files/Unity/Install/2019.2.13f1/Editor/Data/PlaybackEngines/WebGLSupport\\BuildTools\\lib\\modules\\WebGLSupport_VRModule_Dynamic.bc\" --additional-libraries=\"D:/Program Files/Unity/Install/2019.2.13f1/Editor/Data/PlaybackEngines/WebGLSupport\\BuildTools\\lib\\modules\\WebGLSupport_WebGLModule_Dynamic.bc\" --additional-libraries=\"D:/Program Files/Unity/Install/2019.2.13f1/Editor/Data/PlaybackEngines/WebGLSupport\\BuildTools\\lib\\modules\\WebGLSupport_WindModule_Dynamic.bc\" --additional-libraries=\"D:/Program Files/Unity/Install/2019.2.13f1/Editor/Data/PlaybackEngines/WebGLSupport\\BuildTools\\lib\\modules\\WebGLSupport_XRModule_Dynamic.bc\" --profiler-report --map-file-parser=\"D:/Program Files/Unity/Install/2019.2.13f1/Editor/Data/Tools/MapFileParser/MapFileParser.exe\" --directory=\"D:/Documents/Faks/Diplomski Rad Prototiip/WaterSystemPrototype/Water System Prototype/Temp/StagingArea/Data/Managed\" --generatedcppdir=\"D:/Documents/Faks/Diplomski Rad Prototiip/WaterSystemPrototype/Water System Prototype/Temp/StagingArea/Data/il2cppOutput\" ",
"meta_command_line_args": "D:\\Program Files\\Unity\\Install\\2019.2.13f1\\Editor\\Data\\il2cpp/build/il2cpp.exe --convert-to-cpp --dotnetprofile=unityaot --compile-cpp --libil2cpp-static --platform=WebGL --architecture=EmscriptenJavaScript --configuration=Release --outputpath=D:\\Documents\\Faks\\Diplomski Rad Prototiip\\WaterSystemPrototype\\Water System Prototype\\Assets /../Temp/StagingArea/Data\\Native\\build.bc --cachedirectory=D:\\Documents\\Faks\\Diplomski Rad Prototiip\\WaterSystemPrototype\\Water System Prototype\\Assets\\..\\Library/il2cpp_cache --compiler-flags=-Oz -DIL2CPP_EXCEPTION_DISABLED=1  --emit-method-map --additional-libraries=D:/Program Files/Unity/Install/2019.2.13f1/Editor/Data/PlaybackEngines/WebGLSupport\\BuildTools\\lib\\modules\\WebGLSupport_AccessibilityModule_Dynamic.bc --additional-libraries=D:/Program Files/Unity/Install/2019.2.13f1/Editor/Data/PlaybackEngines/WebGLSupport\\BuildTools\\lib\\modules\\WebGLSupport_AIModule_Dynamic.bc --additional-libraries=D:/Program Files/Unity/Install/2019.2.13f1/Editor/Data/PlaybackEngines/WebGLSupport\\BuildTools\\lib\\modules\\WebGLSupport_AndroidJNIModule_Dynamic.bc --additional-libraries=D:/Program Files/Unity/Install/2019.2.13f1/Editor/Data/PlaybackEngines/WebGLSupport\\BuildTools\\lib\\modules\\WebGLSupport_AnimationModule_Dynamic.bc --additional-libraries=D:/Program Files/Unity/Install/2019.2.13f1/Editor/Data/PlaybackEngines/WebGLSupport\\BuildTools\\lib\\modules\\WebGLSupport_ARModule_Dynamic.bc --additional-libraries=D:/Program Files/Unity/Install/2019.2.13f1/Editor/Data/PlaybackEngines/WebGLSupport\\BuildTools\\lib\\modules\\WebGLSupport_AssetBundleModule_Dynamic.bc --additional-libraries=D:/Program Files/Unity/Install/2019.2.13f1/Editor/Data/PlaybackEngines/WebGLSupport\\BuildTools\\lib\\modules\\WebGLSupport_AudioModule_Dynamic.bc --additional-libraries=D:/Program Files/Unity/Install/2019.2.13f1/Editor/Data/PlaybackEngines/WebGLSupport\\BuildTools\\lib\\modules\\WebGLSupport_ClothModule_Dynamic.bc --additional-libraries=D:/Program Files/Unity/Install/2019.2.13f1/Editor/Data/PlaybackEngines/WebGLSupport\\BuildTools\\lib\\modules\\WebGLSupport_CoreModule_Dynamic.bc --additional-libraries=D:/Program Files/Unity/Install/2019.2.13f1/Editor/Data/PlaybackEngines/WebGLSupport\\BuildTools\\lib\\modules\\WebGLSupport_CrashReportingModule_Dynamic.bc --additional-libraries=D:/Program Files/Unity/Install/2019.2.13f1/Editor/Data/PlaybackEngines/WebGLSupport\\BuildTools\\lib\\modules\\WebGLSupport_DirectorModule_Dynamic.bc --additional-libraries=D:/Program Files/Unity/Install/2019.2.13f1/Editor/Data/PlaybackEngines/WebGLSupport\\BuildTools\\lib\\modules\\WebGLSupport_DSPGraphModule_Dynamic.bc --additional-libraries=D:/Program Files/Unity/Install/2019.2.13f1/Editor/Data/PlaybackEngines/WebGLSupport\\BuildTools\\lib\\modules\\WebGLSupport_FileSystemHttpModule_Dynamic.bc --additional-libraries=D:/Program Files/Unity/Install/2019.2.13f1/Editor/Data/PlaybackEngines/WebGLSupport\\BuildTools\\lib\\modules\\WebGLSupport_GameCenterModule_Dynamic.bc --additional-libraries=D:/Program Files/Unity/Install/2019.2.13f1/Editor/Data/PlaybackEngines/WebGLSupport\\BuildTools\\lib\\modules\\WebGLSupport_GridModule_Dynamic.bc --additional-libraries=D:/Program Files/Unity/Install/2019.2.13f1/Editor/Data/PlaybackEngines/WebGLSupport\\BuildTools\\lib\\modules\\WebGLSupport_HotReloadModule_Dynamic.bc --additional-libraries=D:/Program Files/Unity/Install/2019.2.13f1/Editor/Data/PlaybackEngines/WebGLSupport\\BuildTools\\lib\\modules\\WebGLSupport_ImageConversionModule_Dynamic.bc --additional-libraries=D:/Program Files/Unity/Install/2019.2.13f1/Editor/Data/PlaybackEngines/WebGLSupport\\BuildTools\\lib\\modules\\WebGLSupport_IMGUIModule_Dynamic.bc --additional-libraries=D:/Program Files/Unity/Install/2019.2.13f1/Editor/Data/PlaybackEngines/WebGLSupport\\BuildTools\\lib\\modules\\WebGLSupport_InputLegacyModule_Dynamic.bc --additional-libraries=D:/Program Files/Unity/Install/2019.2.13f1/Editor/Data/PlaybackEngines/WebGLSupport\\BuildTools\\lib\\modules\\WebGLSupport_InputModule_Dynamic.bc --additional-libraries=D:/Program Files/Unity/Install/2019.2.13f1/Editor/Data/PlaybackEngines/WebGLSupport\\BuildTools\\lib\\modules\\WebGLSupport_JSONSerializeModule_Dynamic.bc --additional-libraries=D:/Program Files/Unity/Install/2019.2.13f1/Editor/Data/PlaybackEngines/WebGLSupport\\BuildTools\\lib\\modules\\WebGLSupport_LocalizationModule_Dynamic.bc --additional-libraries=D:/Program Files/Unity/Install/2019.2.13f1/Editor/Data/PlaybackEngines/WebGLSupport\\BuildTools\\lib\\modules\\WebGLSupport_ParticleSystemModule_Dynamic.bc --additional-libraries=D:/Program Files/Unity/Install/2019.2.13f1/Editor/Data/PlaybackEngines/WebGLSupport\\BuildTools\\lib\\modules\\WebGLSupport_PerformanceReportingModule_Dynamic.bc --additional-libraries=D:/Program Files/Unity/Install/2019.2.13f1/Editor/Data/PlaybackEngines/WebGLSupport\\BuildTools\\lib\\modules\\WebGLSupport_Physics2DModule_Dynamic.bc --additional-libraries=D:/Program Files/Unity/Install/2019.2.13f1/Editor/Data/PlaybackEngines/WebGLSupport\\BuildTools\\lib\\modules\\WebGLSupport_PhysicsModule_Dynamic.bc --additional-libraries=D:/Program Files/Unity/Install/2019.2.13f1/Editor/Data/PlaybackEngines/WebGLSupport\\BuildTools\\lib\\modules\\WebGLSupport_ProfilerModule_Dynamic.bc --additional-libraries=D:/Program Files/Unity/Install/2019.2.13f1/Editor/Data/PlaybackEngines/WebGLSupport\\BuildTools\\lib\\modules\\WebGLSupport_ScreenCaptureModule_Dynamic.bc --additional-libraries=D:/Program Files/Unity/Install/2019.2.13f1/Editor/Data/PlaybackEngines/WebGLSupport\\BuildTools\\lib\\modules\\WebGLSupport_SharedInternalsModule_Dynamic.bc --additional-libraries=D:/Program Files/Unity/Install/2019.2.13f1/Editor/Data/PlaybackEngines/WebGLSupport\\BuildTools\\lib\\modules\\WebGLSupport_SpriteMaskModule_Dynamic.bc --additional-libraries=D:/Program Files/Unity/Install/2019.2.13f1/Editor/Data/PlaybackEngines/WebGLSupport\\BuildTools\\lib\\modules\\WebGLSupport_SpriteShapeModule_Dynamic.bc --additional-libraries=D:/Program Files/Unity/Install/2019.2.13f1/Editor/Data/PlaybackEngines/WebGLSupport\\BuildTools\\lib\\modules\\WebGLSupport_StreamingModule_Dynamic.bc --additional-libraries=D:/Program Files/Unity/Install/2019.2.13f1/Editor/Data/PlaybackEngines/WebGLSupport\\BuildTools\\lib\\modules\\WebGLSupport_SubstanceModule_Dynamic.bc --additional-libraries=D:/Program Files/Unity/Install/2019.2.13f1/Editor/Data/PlaybackEngines/WebGLSupport\\BuildTools\\lib\\modules\\WebGLSupport_TerrainModule_Dynamic.bc --additional-libraries=D:/Program Files/Unity/Install/2019.2.13f1/Editor/Data/PlaybackEngines/WebGLSupport\\BuildTools\\lib\\modules\\WebGLSupport_TerrainPhysicsModule_Dynamic.bc --additional-libraries=D:/Program Files/Unity/Install/2019.2.13f1/Editor/Data/PlaybackEngines/WebGLSupport\\BuildTools\\lib\\modules\\WebGLSupport_TextCoreModule_Dynamic.bc --additional-libraries=D:/Program Files/Unity/Install/2019.2.13f1/Editor/Data/PlaybackEngines/WebGLSupport\\BuildTools\\lib\\modules\\WebGLSupport_TextRenderingModule_Dynamic.bc --additional-libraries=D:/Program Files/Unity/Install/2019.2.13f1/Editor/Data/PlaybackEngines/WebGLSupport\\BuildTools\\lib\\modules\\WebGLSupport_TilemapModule_Dynamic.bc --additional-libraries=D:/Program Files/Unity/Install/2019.2.13f1/Editor/Data/PlaybackEngines/WebGLSupport\\BuildTools\\lib\\modules\\WebGLSupport_TLSModule_Dynamic.bc --additional-libraries=D:/Program Files/Unity/Install/2019.2.13f1/Editor/Data/PlaybackEngines/WebGLSupport\\BuildTools\\lib\\modules\\WebGLSupport_UIElementsModule_Dynamic.bc --additional-libraries=D:/Program Files/Unity/Install/2019.2.13f1/Editor/Data/PlaybackEngines/WebGLSupport\\BuildTools\\lib\\modules\\WebGLSupport_UIModule_Dynamic.bc --additional-libraries=D:/Program Files/Unity/Install/2019.2.13f1/Editor/Data/PlaybackEngines/WebGLSupport\\BuildTools\\lib\\modules\\WebGLSupport_UmbraModule_Dynamic.bc --additional-libraries=D:/Program Files/Unity/Install/2019.2.13f1/Editor/Data/PlaybackEngines/WebGLSupport\\BuildTools\\lib\\modules\\WebGLSupport_UNETModule_Dynamic.bc --additional-libraries=D:/Program Files/Unity/Install/2019.2.13f1/Editor/Data/PlaybackEngines/WebGLSupport\\BuildTools\\lib\\modules\\WebGLSupport_UnityAnalyticsModule_Dynamic.bc --additional-libraries=D:/Program Files/Unity/Install/2019.2.13f1/Editor/Data/PlaybackEngines/WebGLSupport\\BuildTools\\lib\\modules\\WebGLSupport_UnityConnectModule_Dynamic.bc --additional-libraries=D:/Program Files/Unity/Install/2019.2.13f1/Editor/Data/PlaybackEngines/WebGLSupport\\BuildTools\\lib\\modules\\WebGLSupport_UnityTestProtocolModule_Dynamic.bc --additional-libraries=D:/Program Files/Unity/Install/2019.2.13f1/Editor/Data/PlaybackEngines/WebGLSupport\\BuildTools\\lib\\modules\\WebGLSupport_UnityWebRequestAssetBundleModule_Dynamic.bc --additional-libraries=D:/Program Files/Unity/Install/2019.2.13f1/Editor/Data/PlaybackEngines/WebGLSupport\\BuildTools\\lib\\modules\\WebGLSupport_UnityWebRequestAudioModule_Dynamic.bc --additional-libraries=D:/Program Files/Unity/Install/2019.2.13f1/Editor/Data/PlaybackEngines/WebGLSupport\\BuildTools\\lib\\modules\\WebGLSupport_UnityWebRequestModule_Dynamic.bc --additional-libraries=D:/Program Files/Unity/Install/2019.2.13f1/Editor/Data/PlaybackEngines/WebGLSupport\\BuildTools\\lib\\modules\\WebGLSupport_UnityWebRequestTextureModule_Dynamic.bc --additional-libraries=D:/Program Files/Unity/Install/2019.2.13f1/Editor/Data/PlaybackEngines/WebGLSupport\\BuildTools\\lib\\modules\\WebGLSupport_UnityWebRequestWWWModule_Dynamic.bc --additional-libraries=D:/Program Files/Unity/Install/2019.2.13f1/Editor/Data/PlaybackEngines/WebGLSupport\\BuildTools\\lib\\modules\\WebGLSupport_VehiclesModule_Dynamic.bc --additional-libraries=D:/Program Files/Unity/Install/2019.2.13f1/Editor/Data/PlaybackEngines/WebGLSupport\\BuildTools\\lib\\modules\\WebGLSupport_VFXModule_Dynamic.bc --additional-libraries=D:/Program Files/Unity/Install/2019.2.13f1/Editor/Data/PlaybackEngines/WebGLSupport\\BuildTools\\lib\\modules\\WebGLSupport_VideoModule_Dynamic.bc --additional-libraries=D:/Program Files/Unity/Install/2019.2.13f1/Editor/Data/PlaybackEngines/WebGLSupport\\BuildTools\\lib\\modules\\WebGLSupport_VRModule_Dynamic.bc --additional-libraries=D:/Program Files/Unity/Install/2019.2.13f1/Editor/Data/PlaybackEngines/WebGLSupport\\BuildTools\\lib\\modules\\WebGLSupport_WebGLModule_Dynamic.bc --additional-libraries=D:/Program Files/Unity/Install/2019.2.13f1/Editor/Data/PlaybackEngines/WebGLSupport\\BuildTools\\lib\\modules\\WebGLSupport_WindModule_Dynamic.bc --additional-libraries=D:/Program Files/Unity/Install/2019.2.13f1/Editor/Data/PlaybackEngines/WebGLSupport\\BuildTools\\lib\\modules\\WebGLSupport_XRModule_Dynamic.bc --profiler-report --map-file-parser=D:/Program Files/Unity/Install/2019.2.13f1/Editor/Data/Tools/MapFileParser/MapFileParser.exe --directory=D:/Documents/Faks/Diplomski Rad Prototiip/WaterSystemPrototype/Water System Prototype/Temp/StagingArea/Data/Managed --generatedcppdir=D:/Documents/Faks/Diplomski Rad Prototiip/WaterSystemPrototype/Water System Prototype/Temp/StagingArea/Data/il2cppOutput",
"meta_user_name": "Marko",
"meta_os_version": "Microsoft Windows NT 6.2.9200.0",
"meta_cpu_count": "4"}
